Workbook

Sheet ADDDF
A1: ADDDF_balance-sheet_Annual_As_Originally_Reported | B1: 2019 | C1: 2020 | D1: 2021 | E1: 2022 | F1: 2023
A2: Total Assets | B2: 20680000000 | C2: 21053000000 | D2: 22137000000 | E2: 20296000000 | F2: 18020000000
A3: Total Current Assets | B3: 10934000000 | C3: 12154000000 | D3: 13944000000 | E3: 11732000000 | F3: 9809000000
A4: Cash, Cash Equivalents and Short Term Investments | B4: 2662000000 | C4: 4239000000 | D4: 3937000000 | E4: 966000000 | F4: 2220000000
A5: Cash and Cash Equivalents | B5: 2220000000 | C5: 3994000000 | D5: 3828000000 | E5: 798000000 | F5: 1431000000
A6: Short Term Investments | B6: 442000000 | C6: 245000000 | D6: 109000000 | E6: 168000000 | F6: 789000000
A7: Other Short Term Investments | B7: 442000000 | C7: 245000000 | D7: 109000000 | E7: 168000000 | F7: 789000000
A8: Inventories | B8: 4085000000 | C8: 4397000000 | D8: 4009000000 | E8: 5973000000 | F8: 4525000000
A9: Raw Materials, Consumables and Supplies | B9: 6000000 | C9: 8000000 | D9: 7000000 | E9: 9000000 | F9: 8000000
A10: Work-in-Process | B10: 0 | C10: 0 | D10: 0 | E10: 0 | F10: 0
A11: Finished Goods and Merchandise | B11: 4079000000 | C11: 4389000000 | D11: 4002000000 | E11: 5964000000 | F11: 4516000000
A12: Inventory Allowance/Adjustments
A13: Trade and Other Receivables, Current | B13: 3278000000 | C13: 2713000000 | D13: 3017000000 | E13: 3605000000 | F13: 2062000000
A14: Trade/Accounts Receivable, Current | B14: 2625000000 | C14: 1952000000 | D14: 2175000000 | E14: 2529000000 | F14: 1906000000
A15: Gross Trade/Accounts Receivable, Current | B15: 2814000000 | C15: 2219000000 | D15: 2383000000 | E15: 2759000000 | F15: 2135000000
A16: Allowance/Adjustments for Trade/Accounts Receivable, Current | B16: -189000000 | C16: -267000000 | D16: -208000000 | E16: -230000000 | F16: -229000000
A17: Taxes Receivable, Current | B17: 437000000 | C17: 510000000 | D17: 521000000 | E17: 734000000 | F17: 156000000
A18: Notes Receivable, Current | C18: 6000000 | D18: 12000000 | E18: 0
A19: Accrued Income/Unbilled Revenue/Cost in Excess of Billings, Current | B19: 17000000 | C19: 16000000 | D19: 46000000 | E19: 62000000
A20: Other Receivables, Current | B20: 199000000 | C20: 229000000 | D20: 263000000 | E20: 280000000
A21: Other Current Assets | B21: 425000000 | C21: 385000000 | D21: 356000000 | E21: 420000000 | F21: 1003000000
A22: Derivative Investment and Hedging Assets, Current | B22: 166000000 | C22: 185000000 | D22: 273000000 | E22: 232000000
A23: Prepayments and Deposits, Current | B23: 318000000 | C23: 240000000 | D23: 318000000 | E23: 296000000
A24: Deferred Costs/Assets, Current | E24: 241000000
A25: Assets Held for Sale/Discontinued Operations, Current | C25: 0 | D25: 2033000000 | E25: 0
A26: Total Non-Current Assets | B26: 9746000000 | C26: 8899000000 | D26: 8193000000 | E26: 8563000000 | F26: 8211000000
A27: Net Property, Plant and Equipment | B27: 5311000000 | C27: 4587000000 | D27: 4825000000 | E27: 4943000000 | F27: 4405000000
A28: Gross Property, Plant and Equipment | B28: 7336000000 | C28: 6756000000 | D28: 7141000000 | E28: 7571000000 | F28: 7112000000
A29: Properties | B29: 4627000000 | C29: 4169000000 | D29: 4586000000 | E29: 4890000000 | F29: 4495000000
A30: Land and Improvements | B30: 1842000000 | C30: 1852000000 | D30: 2093000000 | E30: 2290000000 | F30: 2300000000
A31: Leasehold and Improvements | B31: 2785000000 | C31: 2317000000 | D31: 2493000000 | E31: 2600000000 | F31: 2195000000
A32: Construction in Progress and Advance Payments | B32: 221000000 | C32: 258000000 | D32: 212000000 | E32: 230000000 | F32: 156000000
A33: Leased Property, Plant and Equipment | B33: 146000000 | C33: 113000000 | D33: 76000000 | E33: 65000000 | F33: 53000000
A34: Other Property, Plant and Equipment | B34: 2342000000 | C34: 2216000000 | D34: 2267000000 | E34: 2386000000 | F34: 2408000000
A35: Accumulated Depreciation and Impairment | B35: -2025000000 | C35: -2169000000 | D35: -2316000000 | E35: -2628000000 | F35: -2707000000
A36: Accumulated Depreciation | B36: -2025000000 | C36: -2169000000 | D36: -2316000000 | E36: -2628000000 | F36: -2707000000
A37: Accumulated Depreciation of Properties | B37: -520000000 | C37: -620000000 | D37: -704000000 | E37: -849000000 | F37: -922000000
... A45: Other Intangible Assets | B45: 305000000 | C45: 252000000 | D45: 1223000000 | E45: 1425000000 | F45: 442000000
A46: Trademarks and Patents | B46: 1412000000 | C46: 1295000000 | D46: 32000000
A47: Software and Technology | B47: 1086000000 | C47: 1107000000
A48: Accumulated Amortization and Impairment | B48: -1736000000 | C48: -1777000000 | D48: -1305000000 | E48: -1416000000 | F48: -409000000
A49: Accumulated Impairment of Intangible Assets | B49: -402000000 | C49: -376000000 | D49: -402000000 | E49: -420000000 | F49: -409000000
A50: Accumulated Impairment of Goodwill | B50: -402000000 | C50: -376000000 | D50: -402000000 | E50: -420000000 | F50: -409000000
A51: Accumulated Amortization of Intangible Assets | B51: -1334000000 | C51: -1401000000 | D51: -903000000 | E51: -996000000
A52: Accumulated Amortization of Intangibles other than Goodwill | B52: -1334000000 | C52: -1401000000 | D52: -903000000 | E52: -996000000
A53: Accumulated Amortization of Other Intangible Assets | D53: -887000000 | E53: -996000000
A54: Accumulated Amortization of Trademarks and Patents | B54: -553000000 | C54: -545000000 | D54: -16000000
A55: Accumulated Amortization of Software and Technology | B55: -781000000 | C55: -856000000
A56: Total Long Term Investments | B56: 551000000 | C56: 552000000 | D56: 308000000 | E56: 553000000 | F56: 639000000
A57: Investment in Financial Assets, Non-Current | B57: 350000000 | C57: 369000000 | D57: 187000000 | E57: 428000000 | F57: 512000000
A58: Equity Securities/Shares, Non-Current | B58: 81000000 | C58: 84000000 | D58: 83000000 | E58: 88000000 | F58: 85000000
A59: Financial Assets Designated as Fair Value Through Profit or Loss, Non-Current | B59: 120000000 | C59: 99000000 | D59: 87000000 | E59: 314000000 | F59: 390000000
A60: Other Financial Assets, Non-Current | B60: 0 | C60: 20000000 | D60: 17000000 | E60: 26000000 | F60: 37000000
A61: Debt Securities, Non-Current | B61: 149000000 | C61: 166000000
A62: Financial Investment Securities, Available-for-Sale & Held-to-Maturity, Non-Current
A63: Available-for-Sale Securities, Non-Current
A64: Other Investments, Non-Current | B64: 201000000 | C64: 183000000 | D64: 121000000 | E64: 125000000 | F64: 127000000
A65: Derivative Investment and Hedging Assets, Non-Current | B65: 157000000 | C65: 123000000 | D65: 53000000 | E65: 3000000 | F65: 2000000
A66: Trade and Other Receivables, Non-Current | B66: 1000000 | C66: 0 | D66: 0 | E66: 0 | F66: 0
A67: Loans Receivable, Non-Current | B67: 1000000 | C67: 0 | D67: 0 | E67: 0 | F67: 0
A68: Prepayments and Deposits, Non-Current | B68: 211000000 | C68: 193000000 | D68: 165000000 | E68: 155000000 | F68: 125000000
A69: Prepayments, Non-Current | B69: 101000000 | C69: 100000000 | D69: 74000000 | E69: 75000000 | F69: 47000000
A70: Deposits Paid for Business and Fixed Assets, Non-Current | B70: 110000000 | C70: 93000000 | D70: 91000000 | E70: 80000000 | F70: 78000000
A71: Deferred Tax Assets, Non-Current | B71: 1093000000 | C71: 1233000000 | D71: 1263000000 | E71: 1216000000 | F71: 1358000000
A72: Other Non-Current Assets | B72: 3000000 | C72: 2000000 | D72: 0 | E72: 2000000 | F72: 2000000
A73: Total Liabilities | B73: 13623000000 | C73: 14362000000 | D73: 14300000000 | E73: 14945000000 | F73: 13095000000
A74: Total Current Liabilities | B74: 8754000000 | C74: 8827000000 | D74: 8965000000 | E74: 9257000000 | F74: 8043000000
A75: Payables and Accrued Expenses, Current | B75: 6054000000 | C75: 5335000000 | D75: 5757000000 | E75: 5870000000 | F75: 5119000000
... A81: Current Debt and Capital Lease Obligation | B81: 776000000 | C81: 1249000000 | D81: 602000000 | E81: 1170000000 | F81: 1094000000
A82: Current Debt | F82: 0
A83: Notes Payable, Current Debt | F83: 0
A84: Current Portion of Long Term Debt and Capital Lease | B84: 776000000 | C84: 1249000000 | D84: 602000000 | E84: 1170000000 | F84: 1094000000
A85: Current Portion of Long Term Debt | B85: 43000000 | C85: 686000000 | D85: 29000000 | E85: 527000000 | F85: 549000000
A86: Convertible Loans/Debentures, Current Portion of LT Debt | C86: 0 | E86: 498000000 | F86: 500000000
A87: Bank/Institutional Loans, Current Portion of LT Debt | B87: 43000000 | C87: 87000000 | D87: 29000000 | E87: 29000000 | F87: 49000000
A88: Other Current Portion of LT Debt | B88: 0 | C88: 599000000 | E88: 0
A89: Capital Lease Obligations, Current | B89: 733000000 | C89: 563000000 | D89: 573000000 | E89: 643000000 | F89: 545000000
A90: Derivative and Hedging Liabilities, Current | B90: 169000000 | C90: 282000000 | D90: 183000000 | E90: 192000000 | F90: 104000000
A91: Other Financial Liabilities, Current | B91: 66000000 | C91: 164000000 | D91: 110000000 | E91: 164000000 | F91: 67000000
A92: Provisions, Current | B92: 1495000000 | C92: 1653000000 | D92: 1513000000 | E92: 1641000000 | F92: 1360000000
A93: Provision for Employee Entitlements, Current | B93: 49000000 | C93: 44000000 | D93: 55000000 | E93: 52000000 | F93: 37000000
A94: Other Employee-Related Liabilities, Current | B94: 49000000 | C94: 44000000 | D94: 55000000 | E94: 52000000 | F94: 37000000
A95: Other Provisions, Current | B95: 1446000000 | C95: 1609000000 | D95: 1458000000 | E95: 1589000000 | F95: 1323000000
A96: Deferred Liabilities, Current | B96: 63000000 | C96: 75000000 | D96: 156000000 | E96: 148000000 | F96: 223000000
A97: Deferred Income/Customer Advances/Billings in Excess of Cost, Current | B97: 63000000 | C97: 75000000 | D97: 156000000 | E97: 148000000 | F97: 203000000
A98: Other Deferred Liabilities, Current | F98: 20000000
A99: Other Current Liabilities | B99: 130000000 | C99: 69000000 | D99: 51000000 | E99: 72000000 | F99: 75000000
A100: Discontinued Operations Liabilities, Current | D100: 594000000 | E100: 0
A101: Total Non-Current Liabilities | B101: 4869000000 | C101: 5535000000 | D101: 5335000000 | E101: 5688000000 | F101: 5052000000
A102: Financial Liabilities, Non-Current | B102: 4087000000 | C102: 4756000000 | D102: 4781000000 | E102: 5333000000 | F102: 4475000000
A103: Long Term Debt and Capital Lease Obligation | B103: 3994000000 | C103: 4641000000 | D103: 4729000000 | E103: 5289000000 | F103: 4469000000
A104: Long Term Debt | B104: 1595000000 | C104: 2482000000 | D104: 2466000000 | E104: 2946000000 | F104: 2430000000
A105: Notes Payables, Non-Current | B105: 487000000 | C105: 1889000000 | D105: 1890000000 | E105: 2883000000 | F105: 2386000000
A106: Convertible Debentures/Loans, Non-Current | C106: 491000000 | D106: 494000000 | E106: 0 | F106: 0
A107: Bank/Institutional Loans, Non-Current | B107: 122000000 | C107: 102000000 | D107: 82000000 | E107: 63000000 | F107: 44000000
A108: Other Loans, Non-Current | B108: 986000000
A109: Capital Lease Obligations, Non-Current | B109: 2399000000 | C109: 2159000000 | D109: 2263000000 | E109: 2343000000 | F109: 2039000000
A110: Derivative and Hedging Liabilities, Non-Current | B110: 93000000 | C110: 111000000 | D110: 52000000 | E110: 44000000 | F110: 6000000
A111: Other Financial Liabilities, Non-Current | C111: 4000000 | D111: 0
A112: Provisions, Non-Current | B112: 488000000 | C112: 515000000 | D112: 418000000 | E112: 206000000 | F112: 327000000
...

Sheet Income Statement
A1: ADDDF_income-statement_Annual_As_Originally_Reported | B1: 2019 | C1: 2020 | D1: 2021 | E1: 2022 | F1: 2023
A2: Gross Profit | B2: 12293000000 | C2: 9854000000 | D2: 10765000000 | E2: 10644000000 | F2: 10183000000
A3: Total Revenue | B3: 23640000000 | C3: 19844000000 | D3: 21234000000 | E3: 22511000000 | F3: 21427000000
A4: Business Revenue | B4: 23640000000 | C4: 19844000000 | D4: 21234000000 | E4: 22511000000 | F4: 21427000000
A5: Cost of Revenue | B5: -11347000000 | C5: -9990000000 | D5: -10469000000 | E5: -11867000000 | F5: -11244000000
A6: Cost of Goods and Services | B6: -11347000000 | C6: -9990000000 | D6: -10469000000 | E6: -11867000000 | F6: -11244000000
A7: Operating Income/Expenses | B7: -9620000000 | C7: -8993000000 | D7: -8776000000 | E7: -9915000000 | F7: -9904000000
A8: Selling, General and Administrative Expenses | B8: -9691000000 | C8: -8996000000 | D8: -8810000000 | E8: -10015000000 | F8: -9914000000
A9: General and Administrative Expenses | B9: -1652000000 | C9: -1461000000 | D9: -1481000000 | E9: -1651000000 | F9: -1839000000
A10: Selling and Marketing Expenses | B10: -8039000000 | C10: -7535000000 | D10: -7329000000 | E10: -8364000000 | F10: -8075000000
A11: Provisions | B11: 9000000 | C11: 18000000 | D11: 14000000 | E11: 7000000 | F11: 7000000
A12: Other Provisions | B12: 9000000 | C12: 18000000 | D12: 14000000 | E12: 7000000 | F12: 7000000
A13: Other Income/Expense, Operating | B13: 62000000 | C13: -15000000 | D13: 20000000 | E13: 93000000 | F13: 3000000
... A15: Other Expenses, Operating | B15: -134000000 | C15: -119000000 | D15: -76000000 | E15: -182000000 | F15: -137000000
A16: Research and Development Expenses
A17: Total Operating Profit/Loss | B17: 2673000000 | C17: 861000000 | D17: 1989000000 | E17: 729000000 | F17: 279000000
A18: Non-Operating Income/Expense, Total | B18: -115000000 | C18: -286000000 | D18: -200000000 | E18: -341000000 | F18: -216000000
A19: Total Net Finance Income/Expense | B19: -97000000 | C19: -138000000 | D19: -162000000 | E19: -115000000 | F19: -83000000
A20: Net Interest Income/Expense | B20: -110000000 | C20: -139000000 | D20: -165000000 | E20: -114000000 | F20: -121000000
A21: Interest Expense Net of Capitalized Interest | B21: -160000000 | C21: -164000000 | D21: -177000000 | E21: -137000000 | F21: -160000000
A22: Interest Income | B22: 50000000 | C22: 25000000 | D22: 12000000 | E22: 23000000 | F22: 39000000
A23: Other Finance Income/Expenses | B23: 13000000 | C23: 1000000 | D23: 3000000 | E23: -1000000 | F23: 38000000
A24: Other Finance Income | B24: 14000000 | C24: 4000000 | D24: 7000000 | E24: 16000000 | F24: 40000000
A25: Other Finance Expenses | B25: -1000000 | C25: -3000000 | D25: -4000000 | E25: -17000000 | F25: -2000000
A26: Net Investment Income | B26: -5000000 | C26: -37000000 | D26: -37000000 | E26: -166000000 | F26: -121000000
A27: Gain/Loss on Foreign Currency Exchange | B27: -5000000 | C27: -37000000 | D27: -37000000 | E27: -166000000 | F27: -121000000
A28: Irregular Income/Expense | B28: -13000000 | C28: -111000000 | D28: -1000000 | E28: -60000000 | F28: -12000000
... A30: Write Off/Write Down of Other Assets | B30: -18000000 | C30: -114000000 | D30: -6000000 | E30: -63000000 | F30: -19000000
A31: Disposal of Businesses
A32: Impairment/Write Off/Write Down of Capital Assets
A33: Goodwill Impairment/Write Off
A34: Pretax Income | B34: 2558000000 | C34: 575000000 | D34: 1852000000 | E34: 388000000 | F34: 65000000
A35: Provision for Income Tax | B35: -640000000 | C35: -146000000 | D35: -360000000 | E35: -134000000 | F35: -124000000
A36: Net Income before Extraordinary Items and Discontinued Operations | B36: 1918000000 | C36: 429000000 | D36: 1492000000 | E36: 254000000 | F36: -58000000
A37: Discontinued Operations | B37: 59000000 | C37: 13000000 | D37: 666000000 | E37: 384000000 | F37: 44000000
A38: Net Income after Extraordinary Items and Discontinued Operations | B38: 1977000000 | C38: 443000000 | D38: 2158000000 | E38: 638000000 | F38: -14000000
A39: Non-Controlling/Minority Interests | B39: -2000000 | C39: -11000000 | D39: -42000000 | E39: -26000000 | F39: -61000000
A40: Net Income after Non-Controlling/Minority Interests | B40: 1976000000 | C40: 432000000 | D40: 2116000000 | E40: 612000000 | F40: -75000000
A41: Net Income Available to Common Stockholders | B41: 1976000000 | C41: 432000000 | D41: 2116000000 | E41: 612000000 | F41: -75000000
A42: Diluted Net Income Available to Common Stockholders | B42: 1976000000 | C42: 432000000 | D42: 2116000000 | E42: 612000000 | F42: -75000000
A43: Income Statement Supplemental Section
A44: Reported Normalized and Operating Income/Expense Supplemental Section
A45: Total Revenue as Reported, Supplemental | B45: 23640000000 | C45: 19844000000 | D45: 21234000000 | E45: 22511000000 | F45: 21427000000
A46: Reported Total Operating Profit/Loss | B46: 2660000000 | C46: 751000000 | D46: 1986000000 | E46: 669000000 | F46: 268000000
A47: Reported Effective Tax Rate | B47: 0.25 | C47: 0.254 | D47: 0.194 | E47: 0.345 | F47: 1.892
A48: Reported Normalized EBITDA | B48: 3845000000 | C48: 2079000000 | D48: 3066000000 | E48: 1874000000 | F48: 1358000000
A49: Reported Normalized Income
A50: Reported Normalized Operating Profit
A51: Operating Income/Expense, Supplemental Section
A52: Rent Expense, Supplemental | F52: -142000000
A53: Depreciation, Amortization and Depletion, Supplemental | B53: -1214000000 | C53: -1245000000 | D53: -1767000000 | E53: -1221000000 | F53: -1095000000
A54: Depreciation and Amortization, Supplemental | B54: -1214000000 | C54: -1245000000 | D54: -1767000000 | E54: -1221000000 | F54: -1095000000
A55: Depreciation, Supplemental | D55: -1671000000 | E55: -1119000000
A56: Amortization, Supplemental | D56: -96000000 | E56: -102000000
A57: Non-Operating Income/Expense, Supplemental Section
A58: Irregular Items, Supplemental | C58: -119000000 | D58: -8000000 | E58: -150000000 | F58: -74000000
A59: WriteOff/Write Down of Other Assets, Supplemental | C59: -119000000 | D59: -8000000 | E59: -150000000 | F59: -74000000
A60: Employee Costs and Professional Fees, Supplemental Section
A61: Pension and Other Employee Benefits Costs, Supplemental
A62: Dilution to Earnings
A63: Basic EPS | B63: 10 | C63: 2.21 | D63: 10.9 | E63: 3.34 | F63: -0.42
A64: Basic EPS from Continuing Operations | B64: 9.7 | C64: 2.15 | D64: 7.47 | E64: 1.25 | F64: -0.67
A65: Basic EPS from Discontinued Operations | B65: 0.3 | C65: 0.06 | D65: 3.43 | E65: 2.09 | F65: 0.25
A66: Diluted EPS | B66: 10 | C66: 2.21 | D66: 10.9 | E66: 3.34 | F66: -0.42
A67: Diluted EPS from Continuing Operations | B67: 9.7 | C67: 2.15 | D67: 7.47 | E67: 1.25 | F67: -0.67
A68: Diluted EPS from Discontinued Operations | B68: 0.3 | C68: 0.06 | D68: 3.43 | E68: 2.09 | F68: 0.25
A69: Basic Weighted Average Shares Outstanding | B69: 197606107 | C69: 195155924 | D69: 194172984 | E69: 183263629 | F69: 178543596
A70: Diluted Weighted Average Shares Outstanding | B70: 197606107 | C70: 195161729 | D70: 194178081 | E70: 183268087 | F70: 178557615
A71: Total Dividend Per Share | B71: 3.35 | C71: 0 | D71: 3 | E71: 3.3 | F71: 0.7
A72: Regular Dividend Per Share Calc | B72: 3.35 | D72: 3 | E72: 3.3 | F72: 0.7
A73: Reported Normalized Basic EPS
A74: Reported Normalized Diluted EPS
A75: Basic EPS | B75: 10 | C75: 2.21 | D75: 10.9 | E75: 3.34 | F75: -0.42
A76: Diluted EPS | B76: 10 | C76: 2.21 | D76: 10.9 | E76: 3.34 | F76: -0.42
A77: Basic WASO | B77: 197606107 | C77: 195155924 | D77: 194172984 | E77: 183263629 | F77: 178543596
A78: Diluted WASO | B78: 197606107 | C78: 195161729 | D78: 194178081 | E78: 183268087 | F78: 178557615
A79: Fiscal year ends in Dec 31 | EUR
A83: EBITDA | B83: =B17-B54 -> 3887000000 | C83: =C17-C54 -> 2106000000 | D83: =D17-D54 -> 3756000000 | E83: =E17-E54 -> 1950000000 | F83: =F17-F54 -> 1374000000
A85: EBIT | B85: =B17+(-'Cash Flow Statement'!B64) -> 2829000000 | C85: =C17+(-'Cash Flow Statement'!C64) -> 1018000000 | D85: =D17+(-'Cash Flow Statement'!D64) -> 2100000000 | E85: =E17+(-'Cash Flow Statement'!E64) -> 869000000 | F85: =F17+(-'Cash Flow Statement'!F64) -> 442000000

Sheet Cash Flow Statement
A1: ADDDF_cash-flow_Annual_As_Originally_Reported | B1: 2019 | C1: 2020 | D1: 2021 | E1: 2022 | F1: 2023 | G1: TTM
A2: Cash Flow from Operating Activities, Indirect | B2: 2819000000 | C2: 1486000000 | D2: 3192000000 | E2: -543000000 | F2: 2630000000 | G2: 2783000000
A3: Net Cash Flow from Continuing Operating Activities, Indirect | B3: 2828000000 | C3: 1489000000 | D3: 2873000000 | E3: -458000000 | F3: 2630000000 | G3: 2783000000
A4: Cash Generated from Operating Activities | B4: 3519000000 | C4: 1893000000 | D4: 3316000000 | E4: -34000000 | F4: 2938000000 | G4: 3015000000
A5: Income/Loss before Non-Cash Adjustment | B5: 2558000000 | C5: 575000000 | D5: 1852000000 | E5: 388000000 | F5: 65000000 | G5: 735000000
A6: Total Adjustments for Non-Cash Items | B6: 1209000000 | C6: 1568000000 | D6: 1283000000 | E6: 1579000000 | F6: 1449000000 | G6: 1422000000
A7: Depreciation, Amortization and Depletion, Non-Cash Adjustment | B7: 1214000000 | C7: 1370000000 | D7: 1149000000 | E7: 1375000000 | F7: 1212000000 | G7: 1180000000
A8: Depreciation and Amortization, Non-Cash Adjustment | B8: 1214000000 | C8: 1370000000 | D8: 1149000000 | E8: 1375000000 | F8: 1212000000 | G8: 1180000000
A9: Depreciation, Non-Cash Adjustment | F9: 1212000000
A10: Interest and Finance Income/Expenses, Non-Cash Adjustment | B10: 110000000 | C10: 139000000 | D10: 98000000 | E10: 115000000 | F10: 123000000 | G10: 130000000
A11: Net Investment Income/Loss, Non-Cash Adjustment | B11: -1000000 | C11: 35000000 | D11: 51000000 | E11: 85000000 | F11: 144000000 | G11: 117000000
A12: Net Foreign Currency Exchange Gain/Loss, Non-Cash Adjustment | B12: -1000000 | C12: 35000000 | D12: 51000000 | E12: 85000000 | F12: 144000000 | G12: 117000000
A13: Irregular Income/Loss, Non-Cash Adjustment | B13: 3000000 | C13: 22000000 | D13: -21000000 | E13: 12000000 | F13: -22000000 | G13: 22000000
A14: Gain/Loss on Disposals, Non-Cash Adjustment | B14: 11000000 | C14: 28000000 | D14: 13000000 | E14: 16000000 | F14: 20000000 | G14: 48000000
A15: Gain/Loss on Disposal/Sale of Fixed Assets, Non-Cash Adjustment | B15: 11000000 | C15: 28000000 | D15: 13000000 | E15: 16000000 | F15: 20000000 | G15: 48000000
A16: Write Down and Write off of Other Assets, Non-Cash Adjustment | B16: -8000000 | C16: -6000000 | D16: -34000000 | E16: -4000000 | F16: -42000000 | G16: -26000000
A17: Other Non-Cash Items | B17: -12000000 | C17: 2000000 | D17: 6000000 | E17: -8000000 | F17: -8000000 | G17: -27000000
A18: Pension and Employee Benefit Expense, Non-Cash Adjustment | B18: -105000000
A19: Changes in Operating Capital | B19: -248000000 | C19: -250000000 | D19: 181000000 | E19: -2000000000 | F19: 1424000000 | G19: 859000000
A20: Change in Inventories | B20: -505000000 | C20: -503000000 | D20: 125000000 | E20: -1901000000 | F20: 1297000000 | G20: 157000000
A21: Change in Trade and Other Receivables | B21: -694000000 | C21: 394000000 | D21: -170000000 | E21: -820000000 | F21: 995000000 | G21: -196000000
A22: Change in Payables and Accrued Expenses | B22: 951000000 | C22: -141000000 | D22: 226000000 | E22: 721000000 | F22: -868000000 | G22: 898000000
A23: Change in Trade and Other Payables | B23: 951000000 | C23: -141000000 | D23: 226000000 | E23: 721000000 | F23: -868000000 | G23: 898000000
A24: Change in Trade/Accounts Payable | B24: 951000000 | C24: -141000000 | D24: 226000000 | E24: 721000000 | F24: -868000000 | G24: 898000000
A25: Taxes Refund/Paid, Indirect | B25: -692000000 | C25: -404000000 | D25: -444000000 | E25: -424000000 | F25: -307000000 | G25: -255000000
A26: Interest Paid, CFO Indirect
A27: Net Cash Flow from Discontinuing Operating Activities | B27: -9000000 | C27: -3000000 | D27: 320000000 | E27: -85000000 | F27: 0
A28: Cash Flow from Investing Activities | B28: -925000000 | C28: -115000000 | D28: -424000000 | E28: 495000000 | F28: -450000000 | G28: -373000000
A29: Cash Flow from Continuing Investing Activities | B29: -927000000 | C29: -115000000 | D29: -414000000 | E29: 494000000 | F29: -450000000 | G29: -371000000
A30: Purchase/Sale and Disposal of Property, Plant and Equipment, Net | B30: -585000000 | C30: -362000000 | D30: -493000000 | E30: -503000000 | F30: -353000000 | G30: -375000000
A31: Purchase of Property, Plant and Equipment | B31: -598000000 | C31: -379000000 | D31: -494000000 | E31: -504000000 | F31: -363000000 | G31: -383000000
A32: Sale and Disposal of Property, Plant and Equipment | B32: 13000000 | C32: 17000000 | D32: 1000000 | E32: 1000000 | F32: 10000000 | G32: 8000000
A33: Purchase/Sale of Intangibles, Net | B33: -110000000 | C33: -60000000 | D33: -172000000 | E33: -190000000 | F33: -140000000 | G33: -125000000
A34: Purchase of Intangibles | B34: -110000000 | C34: -64000000 | D34: -173000000 | E34: -191000000 | F34: -141000000 | G34: -126000000
A35: Sale of Intangibles | B35: 0 | C35: 4000000 | D35: 1000000 | E35: 1000000 | F35: 1000000 | G35: 1000000
A36: Purchase/Sale of Business, Net | B36: 82000000 | C36: 42000000 | D36: 189000000 | E36: 1177000000 | F36: -19000000 | G36: 100000000
A37: Purchase/Acquisition of Business | F37: -19000000 | G37: 0
A38: Sale of Business | B38: 82000000 | C38: 42000000 | D38: 189000000 | E38: 1177000000 | F38: 0 | G38: 100000000
A39: Purchase/Sale of Investments, Net | B39: -364000000 | C39: 240000000 | D39: 49000000 | E39: -13000000 | F39: 23000000 | G39: -26000000
A40: Purchase of Investments | B40: -364000000 | C40: -49000000 | F40: -34000000
A41: Sale of Investments | C41: 289000000 | D41: 49000000 | F41: 57000000
A42: Interest Received/Paid, CFI | B42: 50000000 | C42: 25000000 | D42: 13000000 | E42: 23000000 | F42: 39000000 | G42: 55000000
A43: Purchase/Sale of Other Non-Current Assets, Net | B43: 0
A44: Sales of Other Non-Current Assets | B44: 0
A45: Net Cash Flow from Discontinuing Investing Activities | B45: 0 | D45: -9000000 | E45: 0 | F45: 0
A46: Cash Flow from Financing Activities | B46: -2273000000 | C46: 479000000 | D46: -2991000000 | E46: -2963000000 | F46: -1425000000 | G46: -1482000000
A47: Cash Flow from Continuing Financing Activities | B47: -2273000000 | C47: 479000000 | D47: -2952000000 | E47: -2957000000 | F47: -1425000000 | G47: -1482000000
A48: Issuance of/Payments for Common Stock, Net | B48: -813000000 | C48: -261000000 | D48: -1005000000 | E48: -2505000000 | F48: -4000000 | G48: -12000000
A49: Proceeds from Issuance of Common Stock | B49: 24000000 | C49: 25000000 | D49: 27000000 | E49: 25000000 | F49: 25000000 | G49: 24000000
A50: Payments for Common Stock | B50: -837000000 | C50: -286000000 | D50: -1032000000 | E50: -2530000000 | F50: -29000000 | G50: -36000000
A51: Issuance of/Repayments for Debt, Net | B51: -42000000 | C51: 1525000000 | D51: -679000000 | E51: 976000000 | F51: -497000000 | G51: -500000000
A52: Issuance of/Repayments for Short Term Debt, Net | B52: -42000000 | C52: 24000000 | D52: -79000000 | E52: -18000000 | F52: 3000000 | G52: 0
A53: Repayments for Short Term Debt | B53: -42000000 | C53: -519000000 | E53: -18000000
A54: Proceeds from Issuance of Short Term Debt | B54: 0 | C54: 543000000
A55: Issuance of/Repayments for Long Term Debt, Net | B55: 0 | C55: 1501000000 | D55: -600000000 | E55: 994000000 | F55: -500000000 | G55: -500000000
A56: Proceeds from Issuance of Long Term Debt | B56: 0 | C56: 1501000000 | E56: 994000000 | F56: 0
A57: Repayments for Long Term Debt | D57: -600000000 | E57: 0 | F57: -500000000 | G57: -500000000
A58: Issuance of/Repayments for Lease Financing | B58: -597000000 | C58: -611000000 | D58: -572000000 | E58: -631000000 | F58: -603000000 | G58: -628000000
A59: Repayments for Lease Financing | B59: -597000000 | C59: -611000000 | D59: -572000000 | E59: -631000000 | F59: -603000000 | G59: -628000000
A60: Net Movement in Non-Controlling/Minority Interest | E60: -27000000 | F60: 0 | G60: -12000000
A61: Cash Dividends and Interest Paid | B61: -820000000 | C61: -157000000 | D61: -696000000 | E61: -750000000 | F61: -288000000 | G61: -300000000
A62: Cash Dividends Paid | B62: -664000000 | D62: -585000000 | E62: -610000000 | F62: -125000000 | G62: -125000000
A63: Common Stock Dividends Paid | F63: -125000000
A64: Interest Paid, CFF | B64: -156000000 | C64: -157000000 | D64: -111000000 | E64: -140000000 | F64: -163000000 | G64: -175000000
A65: Cash Dividends Paid to Non-Controlling/Minority Interests | B65: -2000000 | C65: -17000000 | E65: -22000000 | F65: -33000000 | G65: -32000000
A66: Other Financing Cash Flow | B66: 0
A67: Net Cash Flow from Discontinuing Financing Activities | B67: 0 | D67: -39000000 | E67: -6000000 | F67: 0
A68: Cash and Cash Equivalents, End of Period | B68: 2220000000 | C68: 3994000000 | D68: 3828000000 | E68: 798000000 | F68: 1431000000 | G68: 1781000000
A69: Change in Cash | B69: -379000000 | C69: 1850000000 | D69: -223000000 | E69: -3011000000 | F69: 755000000 | G69: 928000000
A70: Effect of Exchange Rate Changes | B70: -30000000 | C70: -75000000 | D70: 57000000 | E70: -19000000 | F70: -40000000 | G70: -42000000
A71: Other Changes | F71: -82000000 | G71: -60000000
A72: Cash and Cash Equivalents, Beginning of Period | B72: 2629000000 | C72: 2220000000 | D72: 3994000000 | E72: 3828000000 | F72: 798000000 | G72: 954000000
A73: Cash Flow Supplemental Section
A74: Change in Cash as Reported, Supplemental | B74: -410000000 | C74: 1774000000 | D74: -165000000 | E74: -3031000000 | F74: 633000000 | G74: 805000000
A75: Fiscal year ends in Dec 31 | EUR

Sheet Competitors
A1: ` | K1: Under Armour | V1: Puma
A2: `
A3: NKE_income-statement_Annual_As_Originally_Reported | B3: 2019 | C3: 2020 | D3: 2021 | E3: 2022 | F3: 2023 | K3: UAA_income-statement_Annual_As_Originally_Reported | L3: 2019 | M3: 2020 | N3: 2021 | O3: 2022 | P3: 2023 | V3: PUM_income-statement_Annual_As_Originally_Reported | W3: 2019 | X3: 2020 | Y3: 2021 | Z3: 2022 | AA3: 2023
A4: Gross Profit | B4: 17474000000 | C4: 16241000000 | D4: 19962000000 | E4: 21479000000 | F4: 22292000000 | K4: Gross Profit | L4: 2470533000 | M4: 2160095000 | N4: 2861499000 | O4: 2649340000 | P4: 2630253000 | V4: Gross Profit | W4: 2686400000 | X4: 2458000000 | Y4: 3257800000 | Z4: 3902700000 | AA4: 3986600000
A5: Total Revenue | B5: 39117000000 | C5: 37403000000 | D5: 44538000000 | E5: 46710000000 | F5: 51217000000 | K5: Total Revenue | L5: 5267132000 | M5: 4474667000 | N5: 5683466000 | O5: 5903636000 | P5: 5701879000 | V5: Total Revenue | W5: 5502200000 | X5: 5234400000 | Y5: 6805400000 | Z5: 8465100000 | AA5: 8601700000
A6: Business Revenue | B6: 39117000000 | C6: 37403000000 | D6: 44538000000 | E6: 46710000000 | F6: 51217000000 | K6: Business Revenue | L6: 5267132000 | M6: 4474667000 | N6: 5683466000 | O6: 5903636000 | P6: 5701879000 | V6: Business Revenue | W6: 5502200000 | X6: 5234400000 | Y6: 6805400000 | Z6: 8465100000 | AA6: 8601700000
A7: Cost of Revenue | B7: -21643000000 | C7: -21162000000 | D7: -24576000000 | E7: -25231000000 | F7: -28925000000 | K7: Cost of Revenue | L7: -2796599000 | M7: -2314572000 | N7: -2821967000 | O7: -3254296000 | P7: -3071626000 | V7: Cost of Revenue | W7: -2815800000 | X7: -2776400000 | Y7: -3547600000 | Z7: -4562300000 | AA7: -4615100000
A8: Cost of Goods and Services | B8: -21643000000 | C8: -21162000000 | D8: -24576000000 | E8: -25231000000 | F8: -28925000000 | K8: Cost of Goods and Services | L8: -2796599000 | M8: -2314572000 | N8: -2821967000 | O8: -3254296000 | P8: -3071626000 | V8: Cost of Goods and Services | W8: -2815800000 | X8: -2776400000 | Y8: -3547600000 | Z8: -4552100000 | AA8: -4615100000
A9: Operating Income/Expenses | B9: -12702000000 | C9: -13126000000 | D9: -13025000000 | E9: -14804000000 | F9: -16377000000 | K9: Operating Income/Expenses | L9: -2233763000 | M9: -2171934000 | N9: -2334691000 | O9: -2365529000 | P9: -2400502000 | V9: Staff Cost, Cost of Revenue | Z9: -10200000
A10: Selling, General and Administrative Expenses | B10: -12702000000 | C10: -13126000000 | D10: -13025000000 | E10: -14804000000 | F10: -16377000000 | K10: Selling, General and Administrative Expenses | L10: -2233763000 | M10: -2171934000 | N10: -2334691000 | O10: -2365529000 | P10: -2400502000 | V10: Operating Income/Expenses | W10: -2250300000 | X10: -2249200000 | Y10: -2703200000 | Z10: -3262200000 | AA10: -3365100000
A11: General and Administrative Expenses | B11: -8949000000 | C11: -9534000000 | D11: -9911000000 | E11: -10954000000 | F11: -12317000000 | K11: Total Operating Profit/Loss | L11: 236770000 | M11: -11839000 | N11: 526808000 | O11: 283811000 | P11: 229751000 | V11: Selling, General and Administrative Expenses | W11: -2213800000 | X11: -2208700000 | Y11: -2665400000 | Z11: -3213900000 | AA11: -3332400000
A12: Selling and Marketing Expenses | B12: -3753000000 | C12: -3592000000 | D12: -3114000000 | E12: -3850000000 | F12: -4060000000 | K12: Non-Operating Income/Expense, Total | L12: -26928000 | M12: -480705000 | N12: -135931000 | O12: 3954000 | P12: 32323000 | V12: General and Administrative Expenses | W12: -340000000 | X12: -368700000 | Y12: -405200000 | Z12: -465800000 | AA12: -450900000
A13: Total Operating Profit/Loss | B13: 4772000000 | C13: 3115000000 | D13: 6937000000 | E13: 6675000000 | F13: 5915000000 | K13: Total Net Finance Income/Expense | L13: -21240000 | M13: -47259000 | N13: -44300000 | O13: -12826000 | P13: 268000 | V13: Selling and Marketing Expenses | W13: -1873800000 | X13: -1840000000 | Y13: -2260200000 | Z13: -2748100000 | AA13: -2881500000
A14: Non-Operating Income/Expense, Total | B14: 29000000 | C14: -228000000 | D14: -276000000 | E14: -24000000 | F14: 286000000 | K14: Net Interest Income/Expense | L14: -21240000 | M14: -47259000 | N14: -44300000 | O14: -12826000 | P14: -268000 | V14: Research and Development Expenses | W14: -61700000 | X14: -56600000 | Y14: -61700000 | Z14: -82200000 | AA14: -89000000
A15: Total Net Finance Income/Expense | B15: -49000000 | C15: -89000000 | D15: -262000000 | E15: -205000000 | F15: 6000000 | K15: Interest Expense Net of Capitalized Interest | L15: -21240000 | M15: -47259000 | V15: Other Income/Expense, Operating | W15: 25200000 | X15: 16100000 | Y15: 23900000 | Z15: 33900000 | AA15: 56300000
A16: Net Interest Income/Expense | B16: -49000000 | C16: -89000000 | D16: -262000000 | E16: -205000000 | F16: -6000000 | K16: Irregular Income/Expense | L16: . | M16: -601599000 | N16: -40518000 | O16: . | P16: . | V16: Other Income, Operating | W16: 25200000 | X16: 16100000 | Y16: 23900000 | Z16: 33900000 | AA16: 56300000
A17: Other Income/Expense, Non-Operating | B17: 78000000 | C17: -139000000 | D17: -14000000 | E17: 181000000 | F17: 280000000 | K17: Restructuring and Reorganization Income/Expense | L17: . | M17: -601599000 | N17: -33947000 | O17: . | P17: . | V17: Total Operating Profit/Loss | W17: 436100000 | X17: 208800000 | Y17: 554600000 | Z17: 640500000 | AA17: 621500000
A18: Pretax Income | B18: 4801000000 | C18: 2887000000 | D18: 6661000000 | E18: 6651000000 | F18: 6201000000 | K18: Impairment/Write Off/Write Down of Capital Assets | N18: -4750000 | V18: Non-Operating Income/Expense, Total | W18: -18500000 | X18: -46500000 | Y18: -49100000 | Z18: -88900000 | AA18: -143400000
A19: Provision for Income Tax | B19: -772000000 | C19: -348000000 | D19: -934000000 | E19: -605000000 | F19: -1131000000 | K19: Write Off/Write Down of Other Assets | N19: -1821000 | V19: Total Net Finance Income/Expense | W19: -33100000 | X19: -43000000 | Y19: -42700000 | Z19: -58900000 | AA19: -50300000
A20: Net Income before Extraordinary Items and Discontinued Operations | B20: 4029000000 | C20: 2539000000 | D20: 5727000000 | E20: 6046000000 | F20: 5070000000 | K20: Merger and Acquisition Income/Expense | V20: Net Interest Income/Expense | W20: -32400000 | X20: -42500000 | Y20: -42200000 | Z20: -44300000 | AA20: -45300000
A21: Net Income after Extraordinary Items and Discontinued Operations | B21: 4029000000 | C21: 2539000000 | D21: 5727000000 | E21: 6046000000 | F21: 5070000000 | K21: Other Income/Expense, Non-Operating | L21: -5688000 | M21: 168153000 | N21: -51113000 | O21: 16780000 | P21: 32055000 | V21: Interest Expense Net of Capitalized Interest | W21: -47800000 | X21: -77900000 | Y21: -72100000 | Z21: -123700000 | AA21: -158000000
A22: Net Income after Non-Controlling/Minority Interests | B22: 4029000000 | C22: 2539000000 | D22: 5727000000 | E22: 6046000000 | F22: 5070000000 | K22: Pretax Income | L22: 209842000 | M22: -492544000 | N22: 390877000 | O22: 287765000 | P22: 262074000 | V22: Interest Income | W22: 15400000 | X22: 35400000 | Y22: 29900000 | Z22: 79400000 | AA22: 112700000
A23: Net Income Available to Common Stockholders | B23: 4029000000 | C23: 2539000000 | D23: 5727000000 | E23: 6046000000 | F23: 5070000000 | K23: Provision for Income Tax | L23: -70024000 | M23: -49387000 | N23: -32072000 | O23: 101046000 | P23: -30006000 | V23: Other Finance Income/Expenses | W23: -700000 | X23: -500000 | Y23: -500000 | Z23: -14600000 | AA23: -5000000
A24: Diluted Net Income Available to Common Stockholders | B24: 4029000000 | C24: 2539000000 | D24: 5727000000 | E24: 6046000000 | F24: 5070000000 | K24: Earnings from Equity Interest | L24: -47679000 | M24: -7246000 | N24: 1255000 | O24: -2042000 | P24: -26000 | V24: Other Finance Expenses | W24: -700000 | X24: -500000 | Y24: -500000 | Z24: -14600000 | AA24: -5000000
A25: Income Statement Supplemental Section | K25: Net Income before Extraordinary Items and Discontinued Operations | L25: 92139000 | M25: -549177000 | N25: 360060000 | O25: 386769000 | P25: 232042000 | V25: Other Finance Income
A26: Reported Normalized and Operating Income/Expense Supplemental Section | K26: Net Income after Extraordinary Items and Discontinued Operations | L26: 92139000 | M26: -549177000 | N26: 360060000 | O26: 386769000 | P26: 232042000 | V26: Net Investment Income | W26: 10500000 | X26: -3900000 | Y26: -9000000 | Z26: -2200000 | AA26: -69400000
A27: Total Revenue as Reported, Supplemental | B27: 39117000000 | C27: 37403000000 | D27: 44538000000 | E27: 46710000000 | F27: 51217000000 | K27: Net Income after Non-Controlling/Minority Interests | L27: 92139000 | M27: -549177000 | N27: 360060000 | O27: 386769000 | P27: 232042000 | V27: Gain/Loss on Foreign Currency Exchange | W27: 10200000 | X27: -3900000 | Y27: -9000000 | Z27: -2200000 | AA27: -69400000
A28: Reported Effective Tax Rate | B28: 0.16 | C28: 0.12 | D28: 0.14 | E28: 0.09 | F28: 0.18 | K28: Net Income Available to Common Stockholders | L28: 92139000 | M28: -549177000 | N28: 360060000 | O28: 386769000 | P28: 232042000 | V28: Dividend and Investment Income | W28: 300000 | X28: .
A29: Discontinued Operations | K29: Dilution to Earnings | O29: 899000 | P29: 901000 | V29: Income from Associates, JointVentures and Other Participating Interests | W29: .
A30: Basic EPS | B30: 2.55 | C30: 1.63 | D30: 3.64 | E30: 3.83 | F30: 3.27 | K30: Diluted Net Income Available to Common Stockholders | L30: 92139000 | M30: -549177000 | N30: 360060000 | O30: 387668000 | P30: 232943000 | V30: Share of Profit and Interest from Associates | W30: .
A31: Basic EPS from Continuing Operations | B31: 2.55 | C31: 1.63 | D31: 3.64 | E31: 3.83 | F31: 3.27 | K31: Income Statement Supplemental Section | V31: Irregular Income/Expense | W31: 4100000 | X31: 400000 | Y31: 2600000 | Z31: -27800000 | AA31: -23700000
A32: Basic EPS from Discontinued Operations | K32: Reported Normalized and Operating Income/Expense Supplemental Section | V32: Other Irregular Income/Expense | W32: 2100000 | Z32: -27800000 | AA32: -23700000
A33: Diluted EPS | B33: 2.49 | C33: 1.6 | D33: 3.56 | E33: 3.75 | F33: 3.23 | K33: Total Revenue as Reported, Supplemental | L33: 5267132000 | M33: 4474667000 | N33: 5683466000 | O33: 5903636000 | P33: 5701879000 | V33: Fixed Asset Disposals | W33: 2000000 | X33: 400000 | Y33: 2600000
A34: Diluted EPS from Continuing Operations | B34: 2.49 | C34: 1.6 | D34: 3.56 | E34: 3.75 | F34: 3.23 | K34: Reported Total Operating Profit/Loss | L34: 236770000 | M34: -613438000 | N34: 486290000 | O34: 283811000 | P34: 229751000 | V34: Pretax Income | W34: 417600000 | X34: 162300000 | Y34: 505300000 | Z34: 551700000 | AA34: 478300000
A35: Diluted EPS from Discontinued Operations | K35: Reported Normalized Income | M35: -120172000 | N35: 396903000 | O35: 266327000 | P35: 244829000 | V35: Provision for Income Tax | W35: -108600000 | X35: -39200000 | Y35: -128500000 | Z35: -127400000 | AA35: -117800000
A36: Basic Weighted Average Shares Outstanding | B36: 1579700000 | C36: 1591600000 | D36: 1573000000 | E36: 1578800000 | F36: 1551600000 | K36: Reported Effective Tax Rate | L36: 0.33 | M36: -0.1 | N36: 0.08 | O36: -0.35 | P36: 0.11 | V36: Net Income before Extraordinary Items and Discontinued Operations | W36: 309000000 | X36: 123100000 | Y36: 376800000 | Z36: 424300000 | AA36: 360500000
A37: Diluted Weighted Average Shares Outstanding | B37: 1618400000 | C37: 1591600000 | D37: 1609400000 | E37: 1610800000 | F37: 1569800000 | K37: Reported Normalized Operating Profit | M37: 537000 | N37: 527323000 | O37: 303811000 | P37: 309751000 | V37: Net Income after Extraordinary Items and Discontinued Operations | W37: 309000000 | X37: 123100000 | Y37: 376800000 | Z37: 424400000 | AA37: 360600000
A38: Reported Normalized Diluted EPS | K38: Other Adjustments to Net Income Available to Common Stockholders | V38: Non-Controlling/Minority Interests | W38: -46600000 | X38: -44200000 | Y38: -67200000 | Z38: -70900000 | AA38: -55700000
A39: Total Dividend Per Share | B39: 0.86 | C39: 0.95 | D39: 1.07 | E39: 1.19 | F39: 1.32 | K39: Basic EPS | L39: 0.2 | M39: -1.21 | N39: 0.77 | O39: 0.86 | P39: 0.53 | V39: Net Income after Non-Controlling/Minority Interests | W39: 262400000 | X39: 78900000 | Y39: 309600000 | Z39: 353500000 | AA39: 304900000
A40: Regular Dividend Per Share Calc | B40: 0.86 | C40: 0.95 | D40: 1.07 | E40: 1.19 | F40: 1.32 | K40: Basic EPS from Continuing Operations | L40: 0.2 | M40: -1.21 | N40: 0.77 | O40: 0.86 | P40: 0.53 | V40: Net Income Available to Common Stockholders | W40: 262400000 | X40: 78900000 | Y40: 309600000 | Z40: 353500000 | AA40: 304900000
A41: Preferred Dividend Per Share | C41: 0.1 | D41: 0.1 | E41: 0.1 | F41: 0.1 | K41: Diluted EPS | L41: 0.2 | M41: -1.21 | N41: 0.77 | O41: 0.84 | P41: 0.52 | V41: Diluted Net Income Available to Common Stockholders | W41: 262400000 | X41: 78900000 | Y41: 309600000 | Z41: 353500000 | AA41: 304900000
A42: Basic EPS | B42: 2.55 | C42: 1.63 | D42: 3.64 | E42: 3.83 | F42: 3.27 | K42: Diluted EPS from Continuing Operations | L42: 0.2 | M42: -1.21 | N42: 0.77 | O42: 0.84 | P42: 0.52 | V42: Income Statement Supplemental Section
A43: Diluted EPS | B43: 2.49 | C43: 1.6 | D43: 3.56 | E43: 3.75 | F43: 3.23 | K43: Basic Weighted Average Shares Outstanding | L43: 450963000 | M43: 454089000 | N43: 465504000 | O43: 451426000 | P43: 440324000 | V43: Reported Normalized and Operating Income/Expense Supplemental Section
A44: Basic WASO | B44: 1579700000 | C44: 1591600000 | D44: 1573000000 | E44: 1578800000 | F44: 1551600000 | K44: Diluted Weighted Average Shares Outstanding | L44: 454274000 | M44: 454089000 | N44: 468644000 | O44: 461509000 | P44: 451011000 | V44: Total Revenue as Reported, Supplemental | W44: 5502200000 | X44: 5234400000 | Y44: 6805400000 | Z44: 8465100000 | AA44: 8601700000
A45: Diluted WASO | B45: 1618400000 | C45: 1591600000 | D45: 1609400000 | E45: 1610800000 | F45: 1569800000 | K45: Reported Normalized Diluted EPS | M45: -0.26 | N45: 0.85 | O45: 0.58 | P45: 0.54 | V45: Reported Total Operating Profit/Loss | W45: 440200000 | X45: 209200000 | Y45: 557100000 | Z45: 640600000 | AA45: 621600000
A46: Ebit | B46: =B18+(-B110) -> 4954000000 | C46: =C18+(-C110) -> 3027000000 | D46: =D18+(-D110) -> 6954000000 | E46: =E18+(-E110) -> 6941000000 | F46: =F18+(-F110) -> 6548000000 | K46: Reported Normalized Basic EPS | V46: Reported Effective Tax Rate | W46: 0.26 | X46: 0.24 | Y46: 0.25 | Z46: 0.23 | AA46: 0.25
K47: Basic EPS | L47: 0.2 | M47: -1.21 | N47: 0.77 | O47: 0.86 | P47: 0.53 | V47: Reported Normalized EBIT | Y47: 557100000 | Z47: 640600000
K48: Diluted EPS | L48: 0.2 | M48: -1.21 | N48: 0.77 | O48: 0.84 | P48: 0.52 | V48: Reported Normalized Operating Profit
A49: NKE_cash-flow_Annual_As_Originally_Reported | B49: 2019 | C49: 2020 | D49: 2021 | E49: 2022 | F49: 2023 | K49: Basic WASO | L49: 450963000 | M49: 454089000 | N49: 465504000 | O49: 451426000 | P49: 440324000 | V49: Operating Income/Expense, Supplemental Section
A50: Cash Flow from Operating Activities, Indirect | B50: 5903000000 | C50: 2485000000 | D50: 6657000000 | E50: 5188000000 | F50: 5841000000 | K50: Diluted WASO | L50: 454274000 | M50: 454089000 | N50: 468644000 | O50: 461509000 | P50: 451011000 | V50: Depreciation, Amortization and Depletion, Supplemental | W50: -246400000 | X50: -275700000 | Y50: -287300000 | Z50: -332800000 | AA50: -351700000
A51: Net Cash Flow from Continuing Operating Activities, Indirect | B51: 5903000000 | C51: 2485000000 | D51: 6657000000 | E51: 5188000000 | F51: 5841000000 | K51: EBIT | L51: =L11+(-L125) -> 254801000 | M51: =M11+(-M125) -> 16787000 | N51: =N11+(-N125) -> 552034000 | O51: =O11+(-O125) -> 303029000 | P51: =P11+(-P125) -> 234179000 | V51: Depreciation and Amortization, Supplemental | W51: -246400000 | X51: -275700000 | Y51: -287300000 | Z51: -332800000 | AA51: -351700000
A52: Cash Generated from Operating Activities | B52: 5903000000 | C52: 2485000000 | D52: 6657000000 | E52: 5188000000 | F52: 5841000000 | V52: Non-Operating Income/Expense, Supplemental Section
A53: Income/Loss before Non-Cash Adjustment | B53: 4029000000 | C53: 2539000000 | D53: 5727000000 | E53: 6046000000 | F53: 5070000000 | K53: UAA_cash-flow_Annual_As_Originally_Reported | L53: 2019 | M53: 2020 | N53: 2021 | O53: 2023 | P53: 2024 | V53: Irregular Items, Supplemental | W53: . | X53: -18000000 | Y53: -18500000 | Z53: -53800000 | AA53: 6200000
A54: Total Adjustments for Non-Cash Items | B54: 1312000000 | C54: 1191000000 | D54: 885000000 | E54: 802000000 | F54: 1284000000 | K54: Cash Flow from Operating Activities, Indirect | L54: 509031000 | M54: 212864000 | N54: 664829000 | O54: -9914000 | P54: 353970000 | V54: Impairment/Write Off/Write Down of Capital Assets, Supplemental | Y54: -18500000 | Z54: -26000000 | AA54: 6200000
A55: Depreciation, Amortization and Depletion, Non-Cash Adjustment | B55: 720000000 | C55: 1119000000 | D55: 797000000 | E55: 840000000 | F55: 859000000 | K55: Net Cash Flow from Continuing Operating Activities, Indirect | L55: 509031000 | M55: 212864000 | N55: 664829000 | O55: -9914000 | P55: 353970000 | V55: Other Irregular Income/Expense, Supplemental | Z55: -27800000
A56: Depreciation and Amortization, Non-Cash Adjustment | B56: 720000000 | C56: 1119000000 | D56: 797000000 | E56: 840000000 | F56: 859000000 | K56: Cash Generated from Operating Activities | L56: 509031000 | M56: 212864000 | N56: 664829000 | O56: -9914000 | P56: 353970000 | V56: WriteOff/Write Down of Other Assets, Supplemental | W56: . | X56: -18000000
A57: Depreciation, Non-Cash Adjustment | B57: 705000000 | C57: 721000000 | D57: 744000000 | E57: 717000000 | F57: 703000000 | K57: Income/Loss before Non-Cash Adjustment | L57: 92139000 | M57: -549177000 | N57: 360060000 | O57: 386769000 | P57: 232042000 | V57: Employee Costs and Professional Fees, Supplemental Section
A58: Amortization, Non-Cash Adjustment | B58: 15000000 | C58: 398000000 | D58: 53000000 | E58: 123000000 | F58: 156000000 | K58: Total Adjustments for Non-Cash Items | L58: 289900000 | M58: 559133000 | N58: 282230000 | O58: 32031000 | P58: 201423000 | V58: Auditor Fees, Supplemental | W58: -800000 | Y58: -900000
A59: Stock-Based Compensation, Non-Cash Adjustment | B59: 325000000 | C59: 429000000 | D59: 611000000 | E59: 638000000 | F59: 755000000 | K59: Depreciation, Amortization and Depletion, Non-Cash Adjustment | L59: 186425000 | M59: 164984000 | N59: 141144000 | O59: 137620000 | P59: 142590000 | V59: Non-Audit Fees Paid to Auditor, Supplemental | W59: -100000 | Y59: -100000
A60: Deferred Taxes, Non-Cash Adjustment | B60: 34000000 | C60: -380000000 | D60: -385000000 | E60: -650000000 | F60: -117000000 | K60: Depreciation and Amortization, Non-Cash Adjustment | L60: 186425000 | M60: 164984000 | N60: 141144000 | O60: 137620000 | P60: 142590000 | V60: Basic EPS | W60: 1.76 | X60: 0.53 | Y60: 2.07 | Z60: 2.36 | AA60: 2.03
A61: Net Investment Income/Loss, Non-Cash Adjustment | B61: 233000000 | C61: 23000000 | D61: -138000000 | E61: -26000000 | F61: -213000000 | K61: Stock-Based Compensation, Non-Cash Adjustment | L61: 49618000 | M61: 42070000 | N61: 43794000 | O61: 36811000 | P61: 42998000 | V61: Basic EPS from Continuing Operations | W61: 1.76 | X61: 0.53 | Y61: 2.07 | Z61: 2.36 | AA61: 2.03
A62: Net Foreign Currency Exchange Gain/Loss, Non-Cash Adjustment | B62: 233000000 | C62: 23000000 | D62: -138000000 | E62: -26000000 | F62: -213000000 | K62: Deferred Taxes, Non-Cash Adjustment | L62: 38132000 | M62: 43992000 | N62: -2642000 | O62: -152403000 | P62: -23693000 | V62: Diluted EPS | W62: 1.76 | X62: 0.53 | Y62: 2.07 | Z62: 2.36 | AA62: 2.03
A63: Irregular Income/Loss, Non-Cash Adjustment | K63: Interest and Finance Income/Expenses, Non-Cash Adjustment | L63: 254000 | M63: 12070000 | N63: 16891000 | O63: 2192000 | P63: 2034000 | V63: Diluted EPS from Continuing Operations | W63: 1.76 | X63: 0.53 | Y63: 2.07 | Z63: 2.36 | AA63: 2.03
A64: Gain/Loss on Disposals, Non-Cash Adjustment | K64: Other Provisions, Non-Cash Adjustment | L64: -26096000 | M64: 10347000 | N64: -25766000 | O64: 11696000 | P64: 13612000 | V64: Basic Weighted Average Shares Outstanding | W64: 149521683 | X64: 149561440 | Y64: 149588684 | Z64: 149650000 | AA64: 149852251
A65: Gain/Loss on Disposal/Sale of Business, Non-Cash Adjustment | K65: Net Investment Income/Loss, Non-Cash Adjustment | L65: -2073000 | M65: -9295000 | N65: 18877000 | O65: -8463000 | P65: 16080000 | V65: Diluted Weighted Average Shares Outstanding | W65: 149521683 | X65: 149561440 | Y65: 149591763 | Z65: 149660000 | AA65: 149871901
A66: Changes in Operating Capital | B66: 562000000 | C66: -1245000000 | D66: 45000000 | E66: -1660000000 | F66: -513000000 | K66: Net Foreign Currency Exchange Gain/Loss, Non-Cash Adjustment | L66: -2073000 | M66: -9295000 | N66: 18877000 | O66: -8463000 | P66: 16080000 | V66: Total Dividend Per Share | W66: 0.35 | Y66: 0.16 | Z66: 0.72 | AA66: 0.82
A67: Change in Inventories | B67: -490000000 | C67: -1854000000 | D67: 507000000 | E67: -1676000000 | F67: -133000000 | K67: Irregular Income/Loss, Non-Cash Adjustment | L67: 43640000 | M67: 294965000 | N67: 89932000 | O67: 4578000 | P67: 7802000 | V67: Regular Dividend Per Share Calc | W67: 0.35 | Y67: 0.16 | Z67: 0.72 | AA67: 0.82
A68: Change in Trade and Other Receivables | B68: -270000000 | C68: 1239000000 | D68: -1606000000 | E68: -504000000 | F68: 489000000 | K68: Gain/Loss on Disposals, Non-Cash Adjustment | L68: 4640000 | M68: -175578000 | N68: 4468000 | O68: 2619000 | P68: 1623000 | V68: Special Dividend Per Share Calc
A69: Change in Trade/Accounts Receivable | B69: -270000000 | C69: 1239000000 | D69: -1606000000 | E69: -504000000 | F69: 489000000 | K69: Gain/Loss on Disposal/Sale of Fixed Assets, Non-Cash Adjustment | L69: 4640000 | M69: 3740000 | N69: 4468000 | O69: 2619000 | P69: 1623000 | V69: Basic EPS | W69: 1.76 | X69: 0.53 | Y69: 2.07 | Z69: 2.36 | AA69: 2.03
A70: Change in Prepayments and Deposits | B70: -203000000 | C70: -654000000 | D70: -182000000 | E70: -845000000 | F70: -644000000 | K70: Gain/Loss on Disposal/Sale of Business, Non-Cash Adjustment | M70: -179318000 | N70: . | O70: . | V70: Diluted EPS | W70: 1.76 | X70: 0.53 | Y70: 2.07 | Z70: 2.36 | AA70: 2.03
A71: Change in Payables and Accrued Expenses | B71: 1525000000 | C71: 24000000 | D71: 1326000000 | E71: 1365000000 | F71: -225000000 | K71: Gain/Loss on Extinguishment of Debt, Non-Cash Adjustment | N71: 58526000 | O71: . | P71: . | V71: Basic WASO | W71: 149521683 | X71: 149561440 | Y71: 149588684 | Z71: 149650000 | AA71: 149852251
A72: Change in Trade and Other Payables | C72: 24000000 | D72: 1326000000 | E72: 1365000000 | F72: -225000000 | K72: Reorganization and M&A, Non-Cash Adjustment | N72: 26938000 | O72: 1959000 | P72: 6179000 | V72: Diluted WASO | W72: 149521683 | X72: 149561440 | Y72: 149591763 | Z72: 149660000 | AA72: 149871901
A73: Change in Trade/Accounts Payable | C73: 24000000 | D73: 1326000000 | E73: 1365000000 | F73: -225000000 | K73: Write Down and Write off of Other Assets, Non-Cash Adjustment | L73: 39000000 | M73: 470543000 | V73: EBIT | W73: =W17+(-W129) -> 479700000 | X73: =X17+(-X129) -> 251800000 | Y73: =Y17+(-Y129) -> 599000000 | Z73: =Z17+(-Z129) -> 694300000 | AA73: =AA17+(-AA129) -> 715800000
A74: Cash Flow from Investing Activities | B74: -264000000 | C74: -1028000000 | D74: -3800000000 | E74: -1524000000 | F74: 564000000 | K74: Excess Tax Benefit from Stock-Based Compensation, Non-Cash Adjustment | L74: .
A75: Cash Flow from Continuing Investing Activities | B75: -264000000 | C75: -1028000000 | D75: -3800000000 | E75: -1524000000 | F75: 564000000 | K75: Changes in Operating Capital | L75: 126992000 | M75: 202908000 | N75: 22539000 | O75: -428714000 | P75: -79495000 | V75: PUM_cash-flow_Annual_As_Originally_Reported | W75: 2019 | X75: 2020 | Y75: 2021 | Z75: 2022 | AA75: 2023
A76: Purchase/Sale and Disposal of Property, Plant and Equipment, Net | B76: -1114000000 | C76: -1086000000 | D76: -695000000 | E76: -758000000 | F76: -969000000 | K76: Change in Inventories | L76: 149519000 | M76: 15306000 | N76: 93287000 | O76: -373714000 | P76: 216484000 | V76: Cash Flow from Operating Activities, Indirect | W76: 548800000 | X76: 421500000 | Y76: 460100000 | Z76: 418300000 | AA76: 653600000
A77: Purchase of Property, Plant and Equipment | B77: -1119000000 | C77: -1086000000 | D77: -695000000 | E77: -758000000 | F77: -969000000 | K77: Change in Trade and Other Receivables | L77: -45450000 | M77: 167614000 | N77: -31153000 | O77: -62162000 | P77: -3906000 | V77: Net Cash Flow from Continuing Operating Activities, Indirect | W77: 548900000 | X77: 421500000 | Y77: 459900000 | Z77: 418300000 | AA77: 653500000
A78: Sale and Disposal of Property, Plant and Equipment | B78: 5000000 | K78: Change in Trade/Accounts Receivable | L78: -45450000 | M78: 167614000 | N78: -31153000 | O78: -62162000 | P78: -3906000 | V78: Cash Generated from Operating Activities | W78: 660400000 | X78: 510800000 | Y78: 606800000 | Z78: 575700000 | AA78: 834800000
A79: Purchase/Sale of Investments, Net | B79: 850000000 | C79: 27000000 | D79: -3276000000 | E79: -747000000 | F79: 1481000000 | K79: Change in Prepayments and Deposits | L79: 24334000 | M79: 18603000 | N79: 10224000 | O79: -36652000 | P79: -29060000 | V79: Income/Loss before Non-Cash Adjustment | W79: 417600000 | X79: 162300000 | Y79: 505300000 | Z79: 551700000 | AA79: 478300000
A80: Purchase of Investments | B80: -2937000000 | C80: -2426000000 | D80: -9961000000 | E80: -12913000000 | F80: -6059000000 | K80: Change in Other Current Assets | L80: 19966000 | M80: -259735000 | N80: 79782000 | O80: -52795000 | P80: 34920000 | V80: Total Adjustments for Non-Cash Items | W80: 287300000 | X80: 360500000 | Y80: 315800000 | Z80: 367300000 | AA80: 485700000
A81: Sale of Investments | B81: 3787000000 | C81: 2453000000 | D81: 6685000000 | E81: 12166000000 | F81: 7540000000 | K81: Change in Payables and Accrued Expenses | L81: 40471000 | M81: 277859000 | N81: -88767000 | O81: 89639000 | P81: -216154000 | V81: Depreciation, Amortization and Depletion, Non-Cash Adjustment | W81: 246400000 | X81: 293800000 | Y81: 305800000 | Z81: 358700000 | AA81: 357500000
A82: Other Investing Cash Flow | B82: . | C82: 31000000 | D82: 171000000 | E82: -19000000 | F82: 52000000 | K82: Change in Trade and Other Payables | L82: 59458000 | M82: -40673000 | N82: 26027000 | O82: 77558000 | P82: -197887000 | V82: Depreciation and Amortization, Non-Cash Adjustment | W82: 246400000 | X82: 293800000 | Y82: 305800000 | Z82: 358700000 | AA82: 357500000
A83: Purchase/Sale of Other Non-Current Assets, Net | K83: Change in Trade/Accounts Payable | L83: 59458000 | M83: -40673000 | N83: 26027000 | O83: 77558000 | P83: -197887000 | V83: Depreciation, Non-Cash Adjustment | W83: 246400000 | X83: 293800000 | Y83: 305800000 | Z83: 358700000 | AA83: 357500000
A84: Purchase/Sale of Business, Net | K84: Change in Accrued Expenses | L84: -18987000 | M84: 318532000 | N84: -114794000 | O84: 12081000 | P84: -18267000 | V84: Pension and Employee Benefit Expense, Non-Cash Adjustment | W84: -1200000 | X84: -1000000 | Y84: -3700000 | Z84: 500000 | AA84: -1500000
A85: Sale of Business | K85: Change in Other Current Liabilities | L85: -80710000 | M85: -19250000 | N85: -38861000 | O85: 851000 | P85: -21427000 | V85: Interest and Finance Income/Expenses, Non-Cash Adjustment | W85: 33100000 | X85: 43000000 | Y85: 42700000 | Z85: 22100000 | AA85: 62900000
A86: Cash Flow from Financing Activities | B86: -5293000000 | C86: 2491000000 | D86: -1459000000 | E86: -4836000000 | F86: -7447000000 | K86: Change in Other Operating Capital | L86: 18862000 | M86: 2511000 | N86: -1973000 | O86: 6119000 | P86: -60352000 | V86: Net Investment Income/Loss, Non-Cash Adjustment | W86: 1900000 | X86: 26300000 | Y86: -29600000 | Z86: -43600000 | AA86: 60100000
A87: Cash Flow from Continuing Financing Activities | B87: -5293000000 | C87: 2491000000 | D87: -1459000000 | E87: -4836000000 | F87: -7447000000 | K87: Cash Flow from Investing Activities | L87: -147113000 | M87: 66345000 | N87: -68346000 | O87: -152796000 | P87: -105333000 | V87: Net Foreign Currency Exchange Gain/Loss, Non-Cash Adjustment | W87: 1900000 | X87: 26300000 | Y87: -29600000 | Z87: -43600000 | AA87: 60100000
A88: Issuance of/Payments for Common Stock, Net | B88: -4286000000 | C88: -3067000000 | D88: -608000000 | E88: -4014000000 | F88: -5480000000 | K88: Cash Flow from Continuing Investing Activities | L88: -147113000 | M88: 66345000 | N88: -68346000 | O88: -152796000 | P88: -105333000 | V88: Share of Profit/Loss from Associates, Joint Ventures and other Equity Investments, Non-Cash Adjustment | W88: .
A89: Payments for Common Stock | B89: -4286000000 | C89: -3067000000 | D89: -608000000 | E89: -4014000000 | F89: -5480000000 | K89: Purchase/Sale and Disposal of Property, Plant and Equipment, Net | L89: -145802000 | M89: -92291000 | N89: -68346000 | O89: -187796000 | P89: -150333000 | V89: Irregular Income/Loss, Non-Cash Adjustment | W89: 2100000 | X89: 2400000 | Y89: 5100000 | Z89: 1000000 | AA89: -15800000
A90: Issuance of/Repayments for Debt, Net | B90: -331000000 | C90: 6183000000 | D90: -249000000 | E90: 15000000 | F90: -504000000 | K90: Purchase of Property, Plant and Equipment | L90: -145802000 | M90: -92291000 | N90: -69759000 | O90: -187796000 | P90: -150333000 | V90: Gain/Loss on Disposals, Non-Cash Adjustment | W90: 2100000 | X90: 2400000 | Y90: 5100000 | Z90: 1000000 | AA90: -3900000
A91: Issuance of/Repayments for Short Term Debt, Net | B91: -325000000 | C91: 49000000 | D91: -52000000 | E91: 15000000 | F91: -4000000 | K91: Sale and Disposal of Property, Plant and Equipment | L91: . | M91: . | N91: 1413000 | O91: . | P91: . | V91: Gain/Loss on Disposal/Sale of Fixed Assets, Non-Cash Adjustment | W91: 2100000 | X91: 2400000 | Y91: 5100000 | Z91: 1000000 | AA91: -3900000
A92: Issuance of/Repayments for Long Term Debt, Net | B92: -6000000 | C92: 6134000000 | D92: -197000000 | E92: . | F92: -500000000 | K92: Purchase/Sale of Business, Net | M92: 158636000 | N92: . | O92: 35000000 | P92: 45000000 | V92: Write off/Write down/Impairment of Capital Assets Loss/Reversal, Non-Cash Adjustment | AA92: -11900000
A93: Repayments for Long Term Debt | B93: -6000000 | D93: -197000000 | E93: . | F93: -500000000 | K93: Sale of Business | M93: 198916000 | N93: . | O93: 35000000 | P93: 45000000 | V93: Other Non-Cash Items | W93: 5000000 | X93: -4000000 | Y93: -4500000 | Z93: 28600000 | AA93: 22500000
A94: Proceeds from Issuance of Long Term Debt | B94: . | C94: 6134000000 | D94: . | E94: . | K94: Purchase/Acquisition of Business | M94: -40280000 | N94: . | O94: . | V94: Changes in Operating Capital | W94: -44500000 | X94: -12000000 | Y94: -214300000 | Z94: -343300000 | AA94: -129200000
A95: Cash Dividends and Interest Paid | B95: -1332000000 | C95: -1452000000 | D95: -1638000000 | E95: -1837000000 | F95: -2012000000 | K95: Purchase/Sale of Other Non-Current Assets, Net | L95: -1311000 | M95: . | N95: . | V95: Change in Inventories | W95: -188800000 | X95: -109700000 | Y95: -304300000 | Z95: -747000000 | AA95: 352100000
A96: Cash Dividends Paid | B96: -1332000000 | C96: -1452000000 | D96: -1638000000 | E96: -1837000000 | F96: -2012000000 | K96: Purchase of Other Non-Current Assets | L96: -1311000 | M96: . | N96: . | V96: Change in Trade and Other Receivables | W96: -69800000 | X96: -50000000 | Y96: -283200000 | Z96: -209400000 | AA96: -153400000
A97: Common Stock Dividends Paid | B97: -1332000000 | C97: -1452000000 | D97: -1638000000 | K97: Purchase/Sale of Equity Investments | L97: . | M97: . | V97: Change in Other Receivables | AA97: -153400000
A98: Proceeds from Issuance/Exercising of Stock Options/Warrants | B98: 700000000 | C98: 885000000 | D98: 1172000000 | E98: 1151000000 | F98: 651000000 | K98: Purchase of Joint Venture/Associate | L98: . | M98: . | V98: Change in Payables and Accrued Expenses | W98: 214100000 | X98: 147700000 | Y98: 373200000 | Z98: 613100000 | AA98: -327900000
A99: Other Financing Cash Flow | B99: -17000000 | C99: -58000000 | D99: -136000000 | E99: -151000000 | F99: -102000000 | K99: Purchase/Sale of Investments, Net | V99: Change in Trade and Other Payables | W99: 214100000 | X99: 147700000 | Y99: 373200000 | Z99: 613100000 | AA99: -327900000
A100: Issuance of/Repayments for Lease Financing | B100: -27000000 | K100: Purchase of Investments | V100: Change in Trade/Accounts Payable | W100: 214100000 | X100: 147700000 | Y100: 373200000 | Z100: 613100000 | AA100: -327900000
...

Sheet Ratios
B2: Adidas
B3: Ratio | C3: 2019 | D3: 2020 | E3: 2021 | F3: 2022 | G3: 2023 | H3: Significance
B4: Debt to Equity Ratio | C4: =ADDDF!B73/ADDDF!B125 -> 1.9304237 | D4: =ADDDF!C73/ADDDF!C125 -> 2.1464654 | E4: =ADDDF!D73/ADDDF!D125 -> 1.8246778 | F4: =ADDDF!E73/ADDDF!E125 -> 2.7929359 | G4: =ADDDF!F73/ADDDF!F125 -> 2.6588832 | H4: Indicates the proportion of financing from debt versus equity
B5: Short-Term vs. Long-Term Debt | C5: =ADDDF!B74/ADDDF!B101 -> 1.7979051 | D5: =ADDDF!C74/ADDDF!C101 -> 1.5947606 | E5: =ADDDF!D74/ADDDF!D101 -> 1.6804124 | F5: =ADDDF!E74/ADDDF!E101 -> 1.6274613 | G5: =ADDDF!F74/ADDDF!F101 -> 1.5920428 | H5: Evaluate company´s debt maturity profile
B6: Current Ratio | C6: =ADDDF!B3/ADDDF!B74 -> 1.249029 | D6: =ADDDF!C3/ADDDF!C74 -> 1.3769117 | E6: =ADDDF!D3/ADDDF!D74 -> 1.555382 | F6: =ADDDF!E3/ADDDF!E74 -> 1.2673652 | G6: =ADDDF!F3/ADDDF!F74 -> 1.2195698 | H6: indicates short-term liquidity
B7: Debt to Asset Ratio | C7: =ADDDF!B73/ADDDF!B2 -> 0.65875242 | D7: =ADDDF!C73/ADDDF!C2 -> 0.68218306 | E7: =ADDDF!D73/ADDDF!D2 -> 0.64597732 | F7: =ADDDF!E73/ADDDF!E2 -> 0.73635199 | G7: =ADDDF!F73/ADDDF!F2 -> 0.72669256 | H7: Shows the percentage of total assets financed by debt
B8: Net Debt-to-EBITDA Ratio | C8: =(ADDDF!B73-ADDDF!B5)/'Income Statement'!B48 -> 2.9656697 | D8: =(ADDDF!C73-ADDDF!C5)/'Income Statement'!C48 -> 4.987013 | E8: =(ADDDF!D73-ADDDF!D5)/'Income Statement'!D48 -> 3.4155251 | F8: =(ADDDF!E73-ADDDF!E5)/'Income Statement'!E48 -> 7.5490928 | G8: =(ADDDF!F73-ADDDF!F5)/'Income Statement'!F48 -> 8.5891016 | H8: Measures the company’s leverage relative to its operational cash flow.
B9: Return on Equity (ROE) | C9: ='Income Statement'!B42/ADDDF!B125 -> 0.28000567 | D9: ='Income Statement'!C42/ADDDF!C125 -> 0.06456434 | E9: ='Income Statement'!D42/ADDDF!D125 -> 0.27000128 | F9: ='Income Statement'!E42/ADDDF!E125 -> 0.11437115 | G9: ='Income Statement'!F42/ADDDF!F125 -> -0.015228426 | H9: Indicates how efficiently the company generates profit from shareholders’ investments.
B10: EBITDA Margin | C10: ='Income Statement'!B48/'Income Statement'!B3 -> 0.16264805 | D10: ='Income Statement'!C48/'Income Statement'!C3 -> 0.10476718 | E10: ='Income Statement'!D48/'Income Statement'!D3 -> 0.14439107 | F10: ='Income Statement'!E48/'Income Statement'!E3 -> 0.08324819 | G10: ='Income Statement'!F48/'Income Statement'!F3 -> 0.063377981 | H10: Shows operational profitability before accounting for interest, taxes, and depreciation.
B11: EBIT Interest Coverage Ratio | C11: ='Income Statement'!B85/'Cash Flow Statement'!B64*-1 -> 18.134615 | D11: ='Income Statement'!C85/'Cash Flow Statement'!C64*-1 -> 6.4840764 | E11: ='Income Statement'!D85/'Cash Flow Statement'!D64*-1 -> 18.918919 | F11: ='Income Statement'!E85/'Cash Flow Statement'!E64*-1 -> 6.2071429 | G11: ='Income Statement'!F85/'Cash Flow Statement'!F64*-1 -> 2.7116564 | H11: Indicates the company’s ability to pay interest on its debt.
B12: Quick Ratio | C12: =(ADDDF!B3-ADDDF!B8)/ADDDF!B74 -> 0.7823852 | D12: =(ADDDF!C3-ADDDF!C8)/ADDDF!C74 -> 0.87878101 | E12: =(ADDDF!D3-ADDDF!D8)/ADDDF!D74 -> 1.1081985 | F12: =(ADDDF!E3-ADDDF!E8)/ADDDF!E74 -> 0.6221238 | G12: =(ADDDF!F3-ADDDF!F8)/ADDDF!F74 -> 0.65696879 | H12: Focuses on liquid assets available to meet short-term obligations.
B13: Cash Flow-to-Debt Ratio | C13: ='Cash Flow Statement'!B2/ADDDF!B73 -> 0.20692946 | D13: ='Cash Flow Statement'!C2/ADDDF!C73 -> 0.10346748 | E13: ='Cash Flow Statement'!D2/ADDDF!D73 -> 0.22321678 | F13: ='Cash Flow Statement'!E2/ADDDF!E73 -> -0.036333222 | G13: ='Cash Flow Statement'!F2/ADDDF!F73 -> 0.20084002 | H13: Indicates how quickly the company can pay off debt with its operating cash flow.
B14: Free Cash Flow-to-Debt Ratio | C14: =('Cash Flow Statement'!B2-'Cash Flow Statement'!B31)/ADDDF!B73 -> 0.25082581 | D14: =('Cash Flow Statement'!C2-'Cash Flow Statement'!C31)/ADDDF!C73 -> 0.12985657 | E14: =('Cash Flow Statement'!D2-'Cash Flow Statement'!D31)/ADDDF!D73 -> 0.25776224 | F14: =('Cash Flow Statement'!E2-'Cash Flow Statement'!E31)/ADDDF!E73 -> -0.0026095684 | G14: =('Cash Flow Statement'!F2-'Cash Flow Statement'!F31)/ADDDF!F73 -> 0.22856052 | H14: Shows cash available for debt repayment after capital expenditures.
I19: 5 year
B20: Debt to Equity Ratio Comparison | I20: For all Company combine | J20: Adidas | M20: Metrics | N20: Adidas | O20: All Companies Combained
B21: Comapany Name | C21: 2019 | D21: 2020 | E21: 2021 | F21: 2022 | G21: 2023 | I21: =AVERAGE(C22:G25) -> 1.8058237 | J21: =AVERAGE(C22:G22) -> 2.2706772 | K21: Mean | M21: Mean | N21: =AVERAGE(C22:G22) -> 2.2706772 | O21: =AVERAGE(Table6[[2019]:[2023]]) -> 1.8058237
B22: Adidas | C22: =C4 -> 1.9304237 | D22: =D4 -> 2.1464654 | E22: =E4 -> 1.8246778 | F22: =F4 -> 2.7929359 | G22: =G4 -> 2.6588832 | I22: =MEDIAN(C22:G25) -> 1.6616068 | J22: =MEDIAN(C22:G22) -> 2.1464654 | K22: Median | M22: Median | N22: =MEDIAN(Table6[[#This Row],[2019]:[2023]]) -> 2.1464654 | O22: =MEDIAN(Table6[[2019]:[2023]]) -> 1.6616068
B23: Nike | C23: =Competitors!B155/Competitors!B185 -> 1.6235619 | D23: =Competitors!C155/Competitors!C185 -> 2.8909994 | E23: =Competitors!D155/Competitors!D185 -> 1.9560586 | F23: =Competitors!E155/Competitors!E185 -> 1.6386362 | G23: =Competitors!F155/Competitors!F185 -> 1.68002 | I23: =MODE(C22:G25) -> #N/A | J23: =MODE(C22:G22) -> #N/A | K23: Mode | M23: Minimum | N23: =MIN(C22:G22) -> 1.8246778 | O23: =MIN(Table6[[2019]:[2023]]) -> 1.2109158
B24: Under Armour | C24: =Competitors!L175/Competitors!L202 -> 1.252714 | D24: =Competitors!M175/Competitors!M202 -> 2.0015806 | E24: =Competitors!N175/Competitors!N202 -> 1.3893779 | F24: =Competitors!O175/Competitors!O202 -> 1.4304822 | G24: =Competitors!P175/Competitors!P202 -> 1.2109158 | I24: =MIN(C22:G25) -> 1.2109158 | J24: =MIN(C22:G22) -> 1.8246778 | K24: Minimum | M24: Maximum | N24: =MAX(C22:G22) -> 2.7929359 | O24: =MAX(Table6[[2019]:[2023]]) -> 2.8909994
B25: Puma | C25: =Competitors!W207/Competitors!W238 -> 1.2799563 | D25: =Competitors!X207/Competitors!X238 -> 1.655536 | E25: =Competitors!Y207/Competitors!Y238 -> 1.5140663 | F25: =Competitors!Z207/Competitors!Z238 -> 1.6676776 | G25: =Competitors!AA207/Competitors!AA238 -> 1.571506 | I25: =MAX(C22:G25) -> 2.8909994 | J25: =MAX(C22:G22) -> 2.7929359 | K25: Maximum
B28: EBIT Interest Coverage Ratio
B29: Comapany Name | C29: 2019 | D29: 2020 | E29: 2021 | F29: 2022 | G29: 2023
B30: Adidas | C30: =C11 -> 18.134615 | D30: =D11 -> 6.4840764 | E30: =E11 -> 18.918919 | F30: =F11 -> 6.2071429 | G30: =G11 -> 2.7116564
B31: Nike | C31: =Competitors!B46/Competitors!B110*-1 -> 32.379085 | D31: =Competitors!C46/Competitors!C110*-1 -> 21.621429 | E31: =Competitors!D46/Competitors!D110*-1 -> 23.733788 | F31: =Competitors!E46/Competitors!E110*-1 -> 23.934483 | G31: =Competitors!F46/Competitors!F110*-1 -> 18.870317
B32: Under Armour | C32: =Competitors!L51/Competitors!L125*-1 -> 14.131274 | D32: =Competitors!M51/Competitors!M125*-1 -> 0.58642493 | E32: =Competitors!N51/Competitors!N125*-1 -> 21.883533 | F32: =Competitors!O51/Competitors!O125*-1 -> 15.767978 | G32: =Competitors!P51/Competitors!P125*-1 -> 52.885953
B33: Puma | C33: =Competitors!W73/Competitors!W129*-1 -> 11.002294 | D33: =Competitors!X73/Competitors!X129*-1 -> 5.855814 | E33: =Competitors!Y73/Competitors!Y129*-1 -> 13.490991 | F33: =Competitors!Z73/Competitors!Z129*-1 -> 12.905204 | G33: =Competitors!AA73/Competitors!AA129*-1 -> 7.5906681
B36: Return on Capital (ROC)
B37: Comapany Name | C37: 2019 | D37: 2020 | E37: 2021 | F37: 2022 | G37: 2023
B38: Adidas | C38: ='Income Statement'!B85/(ADDDF!B73+ADDDF!B125) -> 0.13679884 | D38: ='Income Statement'!C85/(ADDDF!C73+ADDDF!C125) -> 0.048354154 | E38: ='Income Statement'!D85/(ADDDF!D73+ADDDF!D125) -> 0.094863803 | F38: ='Income Statement'!E85/(ADDDF!E73+ADDDF!E125) -> 0.042816318 | G38: ='Income Statement'!F85/(ADDDF!F73+ADDDF!F125) -> 0.024528302
B39: Nike | C39: =Competitors!B46/(Competitors!B185+Competitors!B155) -> 0.20887971 | D39: =Competitors!C46/(Competitors!C185+Competitors!C155) -> 0.096579669 | E39: =Competitors!D46/(Competitors!D185+Competitors!D155) -> 0.18426073 | F39: =Competitors!E46/(Competitors!E185+Competitors!E155) -> 0.17214355 | G39: =Competitors!F46/(Competitors!F185+Competitors!F155) -> 0.17446911
B40: Under Armour | C40: =Competitors!L51/(Competitors!L175+Competitors!L202) -> 0.052606456 | D40: =Competitors!M51/(Competitors!M175+Competitors!M202) -> 0.0033369591 | F40: =Competitors!O51/(Competitors!O175+Competitors!O202) -> 0.062389092 | G40: =Competitors!P51/(Competitors!P175+Competitors!P202) -> 0.049189684
B41: Puma | C41: =Competitors!W73/(Competitors!L175+Competitors!L202) -> 0.099039317 | D41: =Competitors!X73/(Competitors!M175+Competitors!M202) -> 0.050053393 | E41: =Competitors!Y73/(Competitors!N175+Competitors!N202) -> 0.12000651 | F41: =Competitors!Z73/(Competitors!O175+Competitors!O202) -> 0.14294588 | G41: =Competitors!AA73/(Competitors!P175+Competitors!P202) -> 0.15035497
B43: Operating Income / Sales
B44: Comapany Name | C44: 2019 | D44: 2020 | E44: 2021 | F44: 2022 | G44: 2023
B45: Adidas | C45: ='Income Statement'!B7/'Income Statement'!B3 -> -0.40693739 | D45: ='Income Statement'!C7/'Income Statement'!C3 -> -0.45318484 | E45: ='Income Statement'!D7/'Income Statement'!D3 -> -0.41329943 | F45: ='Income Statement'!E7/'Income Statement'!E3 -> -0.44045133 | G45: ='Income Statement'!F7/'Income Statement'!F3 -> -0.46222056
B46: Nike | C46: =Competitors!B13/Competitors!B5 -> 0.121993 | D46: =Competitors!C13/Competitors!C5 -> 0.08328209 | E46: =Competitors!D13/Competitors!D5 -> 0.15575464 | F46: =Competitors!E13/Competitors!E5 -> 0.14290302 | G46: =Competitors!F13/Competitors!F5 -> 0.115489
B47: Under Armour | C47: =Competitors!L9/Competitors!L5 -> -0.42409474 | D47: =Competitors!M9/Competitors!M5 -> -0.4853845 | E47: =Competitors!N9/Competitors!N5 -> -0.41078648 | F47: =Competitors!O9/Competitors!O5 -> -0.40069018 | G47: =Competitors!P9/Competitors!P5 -> -0.42100192
B48: Puma | C48: =Competitors!W10/Competitors!W5 -> -0.40898186 | D48: =Competitors!X10/Competitors!X5 -> -0.42969586 | E48: =Competitors!Y10/Competitors!Y5 -> -0.39721398 | F48: =Competitors!Z10/Competitors!Z5 -> -0.38537052 | G48: =Competitors!AA10/Competitors!AA5 -> -0.39121336
B50: Long-Term Debt / Capitalization
B51: Comapany Name | C51: 2019 | D51: 2020 | E51: 2021 | F51: 2022 | G51: 2023
B52: Adidas | C52: =ADDDF!B104/(ADDDF!B104+ADDDF!B125) -> 0.18435044 | D52: =ADDDF!C104/(ADDDF!C104+ADDDF!C125) -> 0.27057669 | E52: =ADDDF!D104/(ADDDF!D104+ADDDF!D125) -> 0.23934776 | F52: =ADDDF!E104/(ADDDF!E104+ADDDF!E125) -> 0.3550681 | G52: =ADDDF!F104/(ADDDF!F104+ADDDF!F125) -> 0.33038749
B53: Nike | C53: =Competitors!B180/(Competitors!B180+Competitors!B185) -> 0.27703135 | D53: =Competitors!C180/(Competitors!C180+Competitors!C185) -> 0.53868621 | E53: =Competitors!D180/(Competitors!D180+Competitors!D185) -> 0.42439134 | F53: =Competitors!E180/(Competitors!E180+Competitors!E185) -> 0.36857981 | G53: =Competitors!F180/(Competitors!F180+Competitors!F185) -> 0.38929833
B54: Under Armour | C54: =Competitors!L195/(Competitors!L195+Competitors!L202) -> 0.21609035 | D54: =Competitors!M195/(Competitors!M195+Competitors!M202) -> 0.37452422 | E54: =Competitors!N195/(Competitors!N195+Competitors!N202) -> 0.24078684 | F54: =Competitors!O195/(Competitors!O195+Competitors!O202) -> 0.2523412 | G54: =Competitors!P195/(Competitors!P195+Competitors!P202) -> 0.21646237
B55: Puma | C55: =Competitors!L195/(Competitors!L195+Competitors!L202) -> 0.21609035 | D55: =Competitors!M195/(Competitors!M195+Competitors!M202) -> 0.37452422 | E55: =Competitors!N195/(Competitors!N195+Competitors!N202) -> 0.24078684 | F55: =Competitors!O195/(Competitors!O195+Competitors!O202) -> 0.2523412 | G55: =Competitors!P195/(Competitors!P195+Competitors!P202) -> 0.21646237
B57: Current Ratio
B58: Comapany Name | C58: 2019 | D58: 2020 | E58: 2021 | F58: 2022 | G58: 2023
B59: Adidas | C59: =ADDDF!B3/ADDDF!B74 -> 1.249029 | D59: =ADDDF!C3/ADDDF!C74 -> 1.3769117 | E59: =ADDDF!D3/ADDDF!D74 -> 1.555382 | F59: =ADDDF!E3/ADDDF!E74 -> 1.2673652 | G59: =ADDDF!F3/ADDDF!F74 -> 1.2195698
B60: Nike | C60: =Competitors!B115/Competitors!B156 -> 2.1008136 | D60: =Competitors!C115/Competitors!C156 -> 2.4814099 | E60: =Competitors!D115/Competitors!D156 -> 2.7176969 | F60: =Competitors!E115/Competitors!E156 -> 2.6293569 | G60: =Competitors!F115/Competitors!F156 -> 2.7227744
B61: Under Armour | C61: =Competitors!L132/Competitors!L176 -> 1.9002756 | D61: =Competitors!M132/Competitors!M176 -> 2.2804994 | E61: =Competitors!N132/Competitors!N176 -> 2.3006166 | F61: =Competitors!O132/Competitors!O176 -> 2.1811524 | G61: =Competitors!P132/Competitors!P176 -> 2.4571238
B62: Puma | C62: =Competitors!W144/Competitors!W208 -> 1.5916351 | D62: =Competitors!X144/Competitors!X208 -> 1.3952371 | E62: =Competitors!Y144/Competitors!Y208 -> 1.6122892 | F62: =Competitors!Z144/Competitors!Z208 -> 1.4774534 | G62: =Competitors!AA144/Competitors!AA208 -> 1.5493851
B64: Quick Ratio
B65: Comapany Name | C65: 2019 | D65: 2020 | E65: 2021 | F65: 2022 | G65: 2023
B66: Adidas | C66: =(ADDDF!B3-ADDDF!B8)/ADDDF!B74 -> 0.7823852 | D66: =(ADDDF!C3-ADDDF!C8)/ADDDF!C74 -> 0.87878101 | E66: =(ADDDF!D3-ADDDF!D8)/ADDDF!D74 -> 1.1081985 | F66: =(ADDDF!E3-ADDDF!E8)/ADDDF!E74 -> 0.6221238 | G66: =(ADDDF!F3-ADDDF!F8)/ADDDF!F74 -> 0.65696879
B67: Nike | C67: =(Competitors!B115-Competitors!B123)/Competitors!B156 -> 1.386092 | D67: =(Competitors!C115-Competitors!C123)/Competitors!C156 -> 1.5921053 | E67: =(Competitors!D115-Competitors!D123)/Competitors!D156 -> 2.0091999 | F67: =(Competitors!E115-Competitors!E123)/Competitors!E156 -> 1.8446412 | G67: =(Competitors!F115-Competitors!F123)/Competitors!F156 -> 1.8094209
B68: Under Armour | C68: =(Competitors!L132-Competitors!L135)/Competitors!L176 -> 1.2728126 | D68: =(Competitors!M132-Competitors!M135)/Competitors!M176 -> 1.6465298 | E68: =(Competitors!N132-Competitors!N135)/Competitors!N176 -> 1.7410914 | F68: =(Competitors!O132-Competitors!O135)/Competitors!O176 -> 1.303961 | G68: =(Competitors!P132-Competitors!P135)/Competitors!P176 -> 1.6347068
B69: Puma | C69: =(Competitors!W144-Competitors!W150)/Competitors!W208 -> 0.87953044 | D69: =(Competitors!X144-Competitors!X150)/Competitors!X208 -> 0.78764417 | E69: =(Competitors!Y144-Competitors!Y150)/Competitors!Y208 -> 0.93481173 | F69: =(Competitors!Z144-Competitors!Z150)/Competitors!Z208 -> 0.68888498 | G69: =(Competitors!AA144-Competitors!AA150)/Competitors!AA208 -> 0.83935047
B71: Debt to Capital Ratio
B72: Comapany Name | C72: 2019 | D72: 2020 | E72: 2021 | F72: 2022 | G72: 2023
B73: Adidas | C73: =ADDDF!B73/((Dividend!K23*'Income Statement'!B69)+ADDDF!B73) -> 0.192173 | D73: =ADDDF!C73/((Dividend!L23*'Income Statement'!C69)+ADDDF!C73) -> 0.19809942 | E73: =ADDDF!D73/((Dividend!M23*'Income Statement'!D69)+ADDDF!D73) -> 0.22532246 | F73: =ADDDF!E73/((Dividend!N23*'Income Statement'!E69)+ADDDF!E73) -> 0.39017035 | G73: =ADDDF!F73/((Dividend!O23*'Income Statement'!F69)+ADDDF!F73) -> 0.28482506
B74: Nike | C74: =Competitors!B155/((Dividend!K24*Competitors!B36)+Competitors!B155) -> 0.084004704 | D74: =Competitors!C155/((Dividend!L24*Competitors!C36)+Competitors!C155) -> 0.093728875 | E74: =Competitors!D155/((Dividend!M24*Competitors!D36)+Competitors!D155) -> 0.086970025 | F74: =Competitors!E155/((Dividend!N24*Competitors!E36)+Competitors!E155) -> 0.12746225 | G74: =Competitors!F155/((Dividend!O24*Competitors!F36)+Competitors!F155) -> 0.16693325
B75: Under Armour | C75: =Competitors!L175/((Dividend!K25*Competitors!L43)+Competitors!L175) -> 0.25807977 | D75: =Competitors!M175/((Dividend!L25*Competitors!M43)+Competitors!M175) -> 0.25851057 | E75: =Competitors!N175/((Dividend!M25*Competitors!N43)+Competitors!N175) -> 0.22734638 | F75: =Competitors!O175/((Dividend!N25*Competitors!O43)+Competitors!O175) -> 0.38867784 | G75: =Competitors!P175/((Dividend!O25*Competitors!P43)+Competitors!P175) -> 0.40251465
B76: Puma | C76: =Competitors!W207/((Dividend!K26*Competitors!W64)+Competitors!W207) -> 0.19387575 | D76: =Competitors!X207/((Dividend!L26*Competitors!X64)+Competitors!X207) -> 0.17463504 | E76: =Competitors!Y207/((Dividend!M26*Competitors!Y64)+Competitors!Y207) -> 0.17663579 | F76: =Competitors!Z207/((Dividend!N26*Competitors!Z64)+Competitors!Z207) -> 0.3328785 | G76: =Competitors!AA207/((Dividend!O26*Competitors!AA64)+Competitors!AA207) -> 0.37543908
B78: 5 years statistics of debt to capital Ratio for Adidas and its competitors
C79: For All Company Combine | D79: Adidas
B80: Mean | C80: =AVERAGE(C73:G76) -> 0.23191414 | D80: =AVERAGE(C73:G73) -> 0.25811806
B81: Median | C81: =MEDIAN(C73:G76) -> 0.21171094 | D81: =MEDIAN(C73:G73) -> 0.22532246
B82: Mode | C82: =MODE(C73:G76) -> #N/A | D82: =MODE(C73:G73) -> #N/A
B83: Minimum | C83: =MIN(C73:G76) -> 0.084004704 | D83: =MIN(C73:G73) -> 0.192173
B84: Maximum | C84: =MAX(C73:G76) -> 0.40251465 | D84: =MAX(C73:G73) -> 0.39017035

Sheet Credit Rating
B2: Adidas
B3: Year | C3: S&P Rating | D3: S&P Outlook | E3: Moody's Rating | F3: Moody's Outlook
B4: 2020 | C4: N/A | D4: N/A | E4: N/A | F4: N/A
B5: 2020 | C5: A+ | D5: Stable | E5: A2 | F5: Stable
B6: 2021 | C6: A+ | D6: Stable | E6: A2 | F6: Stable
B7: 2022 | C7: A+ | D7: Negative | E7: A2 | F7: Negative
B8: 2023 | C8: A- | D8: Negative | E8: A3 | F8: Negative | G8: Treasury - adidas Annual Report 2023
G9: Ratings - adidas Group
B11: Nike
B12: Year | C12: S&P Rating | D12: S&P Outlook | E12: Moody's Rating | F12: Moody's Outlook
B13: 2019 | C13: AA- | D13: Stable | E13: A1 | F13: Stable
B14: 2020 | C14: AA- | D14: Stable | E14: A1 | F14: Negative
B15: 2021 | C15: AA- | D15: Stable | E15: A1 | F15: Negative
B16: 2022 | C16: AA- | D16: Stable | E16: A1 | F16: Stable
B17: 2023 | C17: AA- | D17: Stable | E17: A1 | F17: Stable
B21: Under Armour
B22: Year | C22: S&P Rating | D22: S&P Outlook | E22: Moody's Rating | F22: Moody's Outlook
B23: 2019 | C23: BB | D23: Stable | E23: Ba3 | F23: Stable
B24: 2020 | C24: BB | D24: Stable | E24: Ba3 | F24: Stable
B25: 2021 | C25: BB | D25: Stable | E25: Ba2 | F25: Positive
B26: 2022 | C26: BB | D26: Positive | E26: Ba2 | F26: Positive
B27: 2023 | C27: BB | D27: Stable | E27: Ba2 | F27: Stable
B31: Puma
B32: Year | C32: S&P Rating | D32: S&P Outlook | E32: Moody's Rating | F32: Moody's Outlook
B33: 2019 | C33: N/A | D33: N/A | E33: N/A | F33: N/A
B34: 2020 | C34: N/A | D34: N/A | E34: N/A | F34: N/A
B35: 2021 | C35: N/A | D35: N/A | E35: N/A | F35: N/A
B36: 2022 | C36: N/A | D36: N/A | E36: N/A | F36: N/A
B37: 2023 | C37: N/A | D37: N/A | E37: N/A | F37: N/A
B43: T Bond Rate | C43: 0.0248 | D43: German Rates & Bonds - Bloomberg
B44: Interest Coverage Ratio | C44: Rating | D44: Spread (%) | E44: Interest Rate (%)
B45: > 8.50 | C45: Aaa/AAA | D45: 0.004 | E45: =D45+$C$43 -> 0.0288 | I45: =2.72%+D45 -> 0.0312
B46: 6.5 –8.5 | C46: Aa2/AA | D46: 0.007 | E46: =D46+$C$43 -> 0.0318
B47: 5.5 –6.5 | C47: A1/A+ | D47: 0.0085 | E47: =D47+$C$43 -> 0.0333
B48: 4.25 –5.5 | C48: A2/A | D48: 0.01 | E48: =D48+$C$43 -> 0.0348
B49: 3 –4.25 | C49: A3/A- | D49: 0.013 | E49: =D49+$C$43 -> 0.0378
B50: 2.5 -3 | C50: Baa2/BBB | D50: 0.02 | E50: =D50+$C$43 -> 0.0448
B51: 2.25 –2.5 | C51: Ba1/BB+ | D51: 0.03 | E51: =D51+$C$43 -> 0.0548
B52: 2 –2.25 | C52: Ba2/BB | D52: 0.04 | E52: =D52+$C$43 -> 0.0648
B53: 1.75 -2 | C53: B1/B+ | D53: 0.055 | E53: =D53+$C$43 -> 0.0798
B54: 1.5 –1.75 | C54: B2/B | D54: 0.065 | E54: =D54+$C$43 -> 0.0898
B55: 1.25 -1.5 | C55: B3/B- | D55: 0.0725 | E55: =D55+$C$43 -> 0.0973
B56: 0.8 -1.25 | C56: Caa/CCC | D56: 0.0875 | E56: =D56+$C$43 -> 0.1123
B57: 0.65 –0.8 | C57: Ca2/CC | D57: 0.095 | E57: =D57+$C$43 -> 0.1198
... B59: <0.2 | C59: D2/D | D59: 0.12 | E59: =D59+$C$43 -> 0.1448

Sheet WACC Approach Nike
A1: Risk-Free Rate (Rf) | B1: 0.0396 | C1: T Bond Rate | D1: 10-year U.S. Treasury bond yield 1990-2023 | Statista
A2: Market Risk Premium (Rm - Rf) | B2: 0.057 | D2: https://www.statista.com/statistics/664840/average-market-risk-premium-usa
A3: Marginal Tax Rate | B3: =21%+7.6% -> 0.286 | C3: https://taxfoundation.org/data/all/state/state-corporate-income-tax-rates-brackets-2024/
A4: Levered Beta (βL) | B4: 1.03 | I4: adidas AG (ADS.DE) Stock Price, News, Quote & History - Yahoo Finance
A5: Unlevered Beta (βU) | B5: =Q6 -> 0.90107888 | P5: Step-2
A6: Total Debt (D) | B6: =Competitors!F155 -> 23527000000 | P6: Unlevered beta | Q6: =B4/(1+(1-B3)*(B6/B7)) -> 0.90107888
A7: Total Equity € | B7: =Dividend!O24*Competitors!F36 -> 117409572000 | C7: As of Dec 2023
A8: EBIT | B8: =Competitors!F46 -> 6548000000
A9: EBIT Interest Coverage Ratio | B9: =Ratios!G31 -> 18.870317
G10: Step-3
F11: Estimate Cost of Equity
E12: Debt to Capital Ratio | F12: D/E Ratio | G12: Levered Beta | H12: Cost of Equity
A13: =B6/(B6+B7) -> 0.16693325 | E13: 0 | F13: =E13/(1-E13) -> 0 | G13: =$Q$6*(1+(1-$B$3)*(F13)) -> 0.90107888 | H13: =$B$1+G13*$B$2 -> 0.090961496
E14: 0.1 | F14: =E14/(1-E14) -> 0.11111111 | G14: =$Q$6*(1+(1-$B$3)*(F14)) -> 0.97256447 | H14: =$B$1+G14*$B$2 -> 0.095036175
E15: 0.2 | F15: =E15/(1-E15) -> 0.25 | G15: =$Q$6*(1+(1-$B$3)*(F15)) -> 1.0619215 | H15: =$B$1+G15*$B$2 -> 0.10012952
E16: 0.3 | F16: =E16/(1-E16) -> 0.42857143 | G16: =$Q$6*(1+(1-$B$3)*(F16)) -> 1.176809 | H16: =$B$1+G16*$B$2 -> 0.10667811
E17: 0.4 | F17: =E17/(1-E17) -> 0.66666667 | G17: =$Q$6*(1+(1-$B$3)*(F17)) -> 1.3299924 | H17: =$B$1+G17*$B$2 -> 0.11540957
E18: 0.5 | F18: =E18/(1-E18) -> 1 | G18: =$Q$6*(1+(1-$B$3)*(F18)) -> 1.5444492 | H18: =$B$1+G18*$B$2 -> 0.1276336
E19: 0.6 | F19: =E19/(1-E19) -> 1.5 | G19: =$Q$6*(1+(1-$B$3)*(F19)) -> 1.8661344 | H19: =$B$1+G19*$B$2 -> 0.14596966
E20: 0.7 | F20: =E20/(1-E20) -> 2.3333333 | G20: =$Q$6*(1+(1-$B$3)*(F20)) -> 2.4022763 | H20: =$B$1+G20*$B$2 -> 0.17652975
E21: 0.8 | F21: =E21/(1-E21) -> 4 | G21: =$Q$6*(1+(1-$B$3)*(F21)) -> 3.4745602 | H21: =$B$1+G21*$B$2 -> 0.23764993
E22: 0.9 | F22: =E22/(1-E22) -> 9 | G22: =$Q$6*(1+(1-$B$3)*(F22)) -> 6.6914118 | H22: =$B$1+G22*$B$2 -> 0.42101047
E24: Pre-Tax Cost of Debt | F24: =B1 -> 0.0396
E25: Estimate Cost of Debts
D26: Debt to Capital Ratio | E26: D/E Ratio | F26: Debt | G26: EBIT | H26: Interest | I26: Pre-Tax Int. Cov | J26: Likely Rating | K26: Pre-Tax cost of debt | L26: Tax Rate | M26: After Tax Cost of Debt
D27: 0 | E27: =D27/(1-D27) -> 0 | F27: =$B$7*D27 -> 0 | G27: =$B$8 -> 6548000000 | H27: =F27*$F$24 -> 0 | I27: =G27/H27 -> #DIV/0! | J27: ='Credit Rating'!C45 -> Aaa/AAA | K27: =S42 -> 0.0436 | L27: =$B$3 -> 0.286 | M27: =K27*(1-L27) -> 0.0311304
D28: 0.1 | E28: =D28/(1-D28) -> 0.11111111 | F28: =$B$7*D28 -> 11740957200 | G28: =$B$8 -> 6548000000 | H28: =F28*$F$24 -> 4.6494191e+08 | I28: =G28/H28 -> 14.08348 | J28: =Q42 -> Aaa/AAA | K28: =S42 -> 0.0436 | L28: =$B$3 -> 0.286 | M28: =K28*(1-L28) -> 0.0311304
D29: 0.2 | E29: =D29/(1-D29) -> 0.25 | F29: =$B$7*D29 -> 23481914400 | G29: =$B$8 -> 6548000000 | H29: =F29*$F$24 -> 9.2988381e+08 | I29: =G29/H29 -> 7.04174 | J29: =Q43 -> Aa2/AA | K29: =S43 -> 0.0466 | L29: =$B$3 -> 0.286 | M29: =K29*(1-L29) -> 0.0332724
D30: 0.3 | E30: =D30/(1-D30) -> 0.42857143 | F30: =$B$7*D30 -> 35222871600 | G30: =$B$8 -> 6548000000 | H30: =F30*$F$24 -> 1.3948257e+09 | I30: =G30/H30 -> 4.6944933 | J30: =Q44 -> A1/A+ | K30: =S44 -> 0.0481 | L30: =$B$3 -> 0.286 | M30: =K30*(1-L30) -> 0.0343434
D31: 0.4 | E31: =D31/(1-D31) -> 0.66666667 | F31: =$B$7*D31 -> 46963828800 | G31: =$B$8 -> 6548000000 | H31: =F31*$F$24 -> 1.8597676e+09 | I31: =G31/H31 -> 3.52087 | J31: =Q46 -> A3/A- | K31: =S46 -> 0.0526 | L31: =$B$3 -> 0.286 | M31: =K31*(1-L31) -> 0.0375564
D32: 0.5 | E32: =D32/(1-D32) -> 1 | F32: =$B$7*D32 -> 58704786000 | G32: =$B$8 -> 6548000000 | H32: =F32*$F$24 -> 2.3247095e+09 | I32: =G32/H32 -> 2.816696 | J32: =Q46 -> A3/A- | K32: =S46 -> 0.0526 | L32: =$B$3 -> 0.286 | M32: =K32*(1-L32) -> 0.0375564
D33: 0.6 | E33: =D33/(1-D33) -> 1.5 | F33: =$B$7*D33 -> 70445743200 | G33: =$B$8 -> 6548000000 | H33: =F33*$F$24 -> 2.7896514e+09 | I33: =G33/H33 -> 2.3472467 | J33: =Q47 -> Baa2/BBB | K33: =S47 -> 0.0596 | L33: =$B$3 -> 0.286 | M33: =K33*(1-L33) -> 0.0425544
D34: 0.7 | E34: =D34/(1-D34) -> 2.3333333 | F34: =$B$7*D34 -> 82186700400 | G34: =$B$8 -> 6548000000 | H34: =F34*$F$24 -> 3.2545933e+09 | I34: =G34/H34 -> 2.0119257 | J34: =Q48 -> Ba1/BB+ | K34: =S48 -> 0.0696 | L34: =$B$3 -> 0.286 | M34: =K34*(1-L34) -> 0.0496944
D35: 0.8 | E35: =D35/(1-D35) -> 4 | F35: =$B$7*D35 -> 93927657600 | G35: =$B$8 -> 6548000000 | H35: =F35*$F$24 -> 3.7195352e+09 | I35: =G35/H35 -> 1.760435 | J35: =Q49 -> Ba2/BB | K35: =S49 -> 0.0796 | L35: =$B$3 -> 0.286 | M35: =K35*(1-L35) -> 0.0568344
D36: 0.9 | E36: =D36/(1-D36) -> 9 | F36: =$B$7*D36 -> 105668614800 | G36: =$B$8 -> 6548000000 | H36: =F36*$F$24 -> 4.1844771e+09 | I36: =G36/H36 -> 1.5648311 | J36: =Q50 -> B1/B+ | K36: =S50 -> 0.0946 | L36: =$B$3 -> 0.286 | M36: =K36*(1-L36) -> 0.0675444
E40: Nike´s Cost of Capital Schedule | P40: T Bond Rate | Q40: =B1 -> 0.0396 | R40: German Rates & Bonds - Bloomberg
D41: Debt to Capital Ratio | E41: Cost of Equity | F41: After-tax Cost of Debt | G41: Cost of Capital | P41: Interest Coverage Ratio | Q41: Rating | R41: Spread (%) | S41: Interest Rate (%)
D42: 0 | E42: =H13 -> 0.090961496 | F42: =M27 -> 0.0311304 | G42: =((E42*(100%-D42))+(F42*D42)) -> 0.090961496 | P42: > 8.50 | Q42: Aaa/AAA | R42: 0.004 | S42: =$Q$40+R42 -> 0.0436
D43: 0.1 | E43: =H14 -> 0.095036175 | F43: =M28 -> 0.0311304 | G43: =((E43*(100%-D43))+(F43*D43)) -> 0.088645597 | P43: 6.5 –8.5 | Q43: Aa2/AA | R43: 0.007 | S43: =$Q$40+R43 -> 0.0466
D44: 0.2 | E44: =H15 -> 0.10012952 | F44: =M29 -> 0.0332724 | G44: =((E44*(100%-D44))+(F44*D44)) -> 0.086758099 | P44: 5.5 –6.5 | Q44: A1/A+ | R44: 0.0085 | S44: =$Q$40+R44 -> 0.0481
D45: 0.3 | E45: =H16 -> 0.10667811 | F45: =M30 -> 0.0343434 | G45: =((E45*(100%-D45))+(F45*D45)) -> 0.0849777 | P45: 4.25 –5.5 | Q45: A2/A | R45: 0.01 | S45: =$Q$40+R45 -> 0.0496
D46: 0.4 | E46: =H17 -> 0.11540957 | F46: =M31 -> 0.0375564 | G46: =((E46*(100%-D46))+(F46*D46)) -> 0.084268301 | P46: 3 –4.25 | Q46: A3/A- | R46: 0.013 | S46: =$Q$40+R46 -> 0.0526
D47: 0.5 | E47: =H18 -> 0.1276336 | F47: =M32 -> 0.0375564 | G47: =((E47*(100%-D47))+(F47*D47)) -> 0.082595002 | P47: 2.5 -3 | Q47: Baa2/BBB | R47: 0.02 | S47: =$Q$40+R47 -> 0.0596
D48: 0.6 | E48: =H19 -> 0.14596966 | F48: =M33 -> 0.0425544 | G48: =((E48*(100%-D48))+(F48*D48)) -> 0.083920503 | P48: 2.25 –2.5 | Q48: Ba1/BB+ | R48: 0.03 | S48: =$Q$40+R48 -> 0.0696
D49: 0.7 | E49: =H20 -> 0.17652975 | F49: =M34 -> 0.0496944 | G49: =((E49*(100%-D49))+(F49*D49)) -> 0.087745005 | P49: 2 –2.25 | Q49: Ba2/BB | R49: 0.04 | S49: =$Q$40+R49 -> 0.0796
D50: 0.8 | E50: =H21 -> 0.23764993 | F50: =M35 -> 0.0568344 | G50: =((E50*(100%-D50))+(F50*D50)) -> 0.092997506 | P50: 1.75 -2 | Q50: B1/B+ | R50: 0.055 | S50: =$Q$40+R50 -> 0.0946
D51: 0.9 | E51: =H22 -> 0.42101047 | F51: =M36 -> 0.0675444 | G51: =((E51*(100%-D51))+(F51*D51)) -> 0.10289101 | P51: 1.5 –1.75 | Q51: B2/B | R51: 0.065 | S51: =$Q$40+R51 -> 0.1046
P52: 1.25 -1.5 | Q52: B3/B- | R52: 0.0725 | S52: =$Q$40+R52 -> 0.1121
P53: 0.8 -1.25 | Q53: Caa/CCC | R53: 0.0875 | S53: =$Q$40+R53 -> 0.1271
P54: 0.65 –0.8 | Q54: Ca2/CC | R54: 0.095 | S54: =$Q$40+R54 -> 0.1346
P55: 0.2 –0.65 | Q55: C2/C | R55: 0.105 | S55: =$Q$40+R55 -> 0.1446
P56: <0.2 | Q56: D2/D | R56: 0.12 | S56: =$Q$40+R56 -> 0.1596

Sheet WACC Approach Under Armour
A1: Risk-Free Rate (Rf) | B1: 0.0396 | C1: T Bond Rate | D1: 10-year U.S. Treasury bond yield 1990-2023 | Statista
A2: Market Risk Premium (Rm - Rf) | B2: 0.057 | D2: Average market risk premium Germany 2023 | Statista
A3: Marginal Tax Rate | B3: =21%+8.25% -> 0.2925 | C3: 2024 State Corporate Income Tax Rates & Brackets
A4: Levered Beta (βL) | B4: 1.66 | I4: adidas AG (ADS.DE) Stock Price, News, Quote & History - Yahoo Finance
A5: Unlevered Beta (βU) | B5: =Q6 -> 1.1241818 | P5: Step-2
A6: Total Debt (D) | B6: =Competitors!P175 -> 2607448000 | P6: Unlevered beta | Q6: =B4/(1+(1-B3)*(B6/B7)) -> 1.1241818
A7: Total Equity € | B7: =Dividend!O25*Competitors!P43 -> 3.870448e+09 | C7: As of Dec 2023 | D7: adidas AG (ADS.DE) Stock Historical Prices & Data - Yahoo Finance
A8: EBIT | B8: =Competitors!P51 -> 234179000
A9: EBIT Interest Coverage Ratio | B9: =Ratios!G32 -> 52.885953
A10: Pre-Tax Cost of Debt | G10: Step-3
F11: Estimate Cost of Equity
E12: Debt to Capital Ratio | F12: D/E Ratio | G12: Levered Beta | H12: Cost of Equity
A13: =B6/(B6+B7) -> 0.40251465 | B13: =A13+1 -> 1.4025146 | E13: 0 | F13: =E13/(1-E13) -> 0 | G13: =$Q$6*(1+(1-$B$3)*(F13)) -> 1.1241818 | H13: =$B$1+G13*$B$2 -> 0.10367836
E14: 0.1 | F14: =E14/(1-E14) -> 0.11111111 | G14: =$Q$6*(1+(1-$B$3)*(F14)) -> 1.212555 | H14: =$B$1+G14*$B$2 -> 0.10871564
E15: 0.2 | F15: =E15/(1-E15) -> 0.25 | G15: =$Q$6*(1+(1-$B$3)*(F15)) -> 1.3230215 | H15: =$B$1+G15*$B$2 -> 0.11501223
E16: 0.3 | F16: =E16/(1-E16) -> 0.42857143 | G16: =$Q$6*(1+(1-$B$3)*(F16)) -> 1.4650498 | H16: =$B$1+G16*$B$2 -> 0.12310784
E17: 0.4 | F17: =E17/(1-E17) -> 0.66666667 | G17: =$Q$6*(1+(1-$B$3)*(F17)) -> 1.6544209 | H17: =$B$1+G17*$B$2 -> 0.13390199
E18: 0.5 | F18: =E18/(1-E18) -> 1 | G18: =$Q$6*(1+(1-$B$3)*(F18)) -> 1.9195405 | H18: =$B$1+G18*$B$2 -> 0.14901381
E19: 0.6 | F19: =E19/(1-E19) -> 1.5 | G19: =$Q$6*(1+(1-$B$3)*(F19)) -> 2.3172198 | H19: =$B$1+G19*$B$2 -> 0.17168153
E20: 0.7 | F20: =E20/(1-E20) -> 2.3333333 | G20: =$Q$6*(1+(1-$B$3)*(F20)) -> 2.9800187 | H20: =$B$1+G20*$B$2 -> 0.20946106
E21: 0.8 | F21: =E21/(1-E21) -> 4 | G21: =$Q$6*(1+(1-$B$3)*(F21)) -> 4.3056164 | H21: =$B$1+G21*$B$2 -> 0.28502014
E22: 0.9 | F22: =E22/(1-E22) -> 9 | G22: =$Q$6*(1+(1-$B$3)*(F22)) -> 8.2824097 | H22: =$B$1+G22*$B$2 -> 0.51169735
E24: Risk free rate | F24: =B1 -> 0.0396
E25: Estimate Cost of Debts
D26: Debt to Capital Ratio | E26: D/E Ratio | F26: Debt | G26: EBIT | H26: Interest | I26: Pre-Tax Int. Cov | J26: Likely Rating | K26: Pre-Tax cost of debt | L26: Tax Rate | M26: After Tax Cost of Debt
D27: 0 | E27: =D27/(1-D27) -> 0 | F27: =$B$7*D27 -> 0 | G27: =$B$8 -> 234179000 | H27: =F27*$F$24 -> 0 | I27: =G27/H27 -> #DIV/0! | J27: =R39 -> Aaa/AAA | K27: =T39 -> 0.0436 | L27: =$B$3 -> 0.2925 | M27: =K27*(1-L27) -> 0.030847
D28: 0.1 | E28: =D28/(1-D28) -> 0.11111111 | F28: =$B$7*D28 -> 387044796 | G28: =$B$8 -> 234179000 | H28: =F28*$F$24 -> 15326974 | I28: =G28/H28 -> 15.27888 | J28: =R39 -> Aaa/AAA | K28: =T39 -> 0.0436 | L28: =$B$3 -> 0.2925 | M28: =K28*(1-L28) -> 0.030847
D29: 0.2 | E29: =D29/(1-D29) -> 0.25 | F29: =$B$7*D29 -> 774089592 | G29: =$B$8 -> 234179000 | H29: =F29*$F$24 -> 30653948 | I29: =G29/H29 -> 7.6394402 | J29: =R39 -> Aaa/AAA | K29: =T39 -> 0.0436 | L29: =$B$3 -> 0.2925 | M29: =K29*(1-L29) -> 0.030847
D30: 0.3 | E30: =D30/(1-D30) -> 0.42857143 | F30: =$B$7*D30 -> 1.1611344e+09 | G30: =$B$8 -> 234179000 | H30: =F30*$F$24 -> 45980922 | I30: =G30/H30 -> 5.0929601 | J30: =R41 -> A1/A+ | K30: =T41 -> 0.0481 | L30: =$B$3 -> 0.2925 | M30: =K30*(1-L30) -> 0.03403075
D31: 0.4 | E31: =D31/(1-D31) -> 0.66666667 | F31: =$B$7*D31 -> 1548179184 | G31: =$B$8 -> 234179000 | H31: =F31*$F$24 -> 61307896 | I31: =G31/H31 -> 3.8197201 | J31: =R42 -> A2/A | K31: =T42 -> 0.0496 | L31: =$B$3 -> 0.2925 | M31: =K31*(1-L31) -> 0.035092
D32: 0.5 | E32: =D32/(1-D32) -> 1 | F32: =$B$7*D32 -> 1.935224e+09 | G32: =$B$8 -> 234179000 | H32: =F32*$F$24 -> 76634870 | I32: =G32/H32 -> 3.0557761 | J32: =R43 -> A3/A- | K32: =T43 -> 0.0526 | L32: =$B$3 -> 0.2925 | M32: =K32*(1-L32) -> 0.0372145
D33: 0.6 | E33: =D33/(1-D33) -> 1.5 | F33: =$B$7*D33 -> 2.3222688e+09 | G33: =$B$8 -> 234179000 | H33: =F33*$F$24 -> 91961844 | I33: =G33/H33 -> 2.5464801 | J33: =R43 -> A3/A- | K33: =T43 -> 0.0526 | L33: =$B$3 -> 0.2925 | M33: =K33*(1-L33) -> 0.0372145
D34: 0.7 | E34: =D34/(1-D34) -> 2.3333333 | F34: =$B$7*D34 -> 2.7093136e+09 | G34: =$B$8 -> 234179000 | H34: =F34*$F$24 -> 1.0728882e+08 | I34: =G34/H34 -> 2.1826972 | J34: =R44 -> Baa2/BBB | K34: =T44 -> 0.0596 | L34: =$B$3 -> 0.2925 | M34: =K34*(1-L34) -> 0.042167
D35: 0.8 | E35: =D35/(1-D35) -> 4 | F35: =$B$7*D35 -> 3096358368 | G35: =$B$8 -> 234179000 | H35: =F35*$F$24 -> 1.2261579e+08 | I35: =G35/H35 -> 1.90986 | J35: =R45 -> Ba1/BB+ | K35: =T45 -> 0.0696 | L35: =$B$3 -> 0.2925 | M35: =K35*(1-L35) -> 0.049242
D36: 0.9 | E36: =D36/(1-D36) -> 9 | F36: =$B$7*D36 -> 3.4834032e+09 | G36: =$B$8 -> 234179000 | H36: =F36*$F$24 -> 1.3794277e+08 | I36: =G36/H36 -> 1.6976534 | J36: =R46 -> Ba2/BB | K36: =T46 -> 0.0796 | L36: =$B$3 -> 0.2925 | M36: =K36*(1-L36) -> 0.056317
Q37: T Bond Rate | R37: =B1 -> 0.0396
Q38: Interest Coverage Ratio | R38: Rating | S38: Spread (%) | T38: Interest Rate (%)
Q39: > 8.50 | R39: Aaa/AAA | S39: 0.004 | T39: =$R$37+S39 -> 0.0436
E40: Under Armour´s Cost of Capital Schedule | Q40: 6.5 –8.5 | R40: Aa2/AA | S40: 0.007 | T40: =$R$37+S40 -> 0.0466
D41: Debt to Capital Ratio | E41: Cost of Equity | F41: After-tax Cost of Debt | G41: Cost of Capital | Q41: 5.5 –6.5 | R41: A1/A+ | S41: 0.0085 | T41: =$R$37+S41 -> 0.0481
D42: 0 | E42: =H13 -> 0.10367836 | F42: =M27 -> 0.030847 | G42: =((E42*(100%-D42))+(F42*D42)) -> 0.10367836 | Q42: 4.25 –5.5 | R42: A2/A | S42: 0.01 | T42: =$R$37+S42 -> 0.0496
D43: 0.1 | E43: =H14 -> 0.10871564 | F43: =M28 -> 0.030847 | G43: =((E43*(100%-D43))+(F43*D43)) -> 0.10092877 | Q43: 3 –4.25 | R43: A3/A- | S43: 0.013 | T43: =$R$37+S43 -> 0.0526
D44: 0.2 | E44: =H15 -> 0.11501223 | F44: =M29 -> 0.030847 | G44: =((E44*(100%-D44))+(F44*D44)) -> 0.09817918 | Q44: 2.5 -3 | R44: Baa2/BBB | S44: 0.02 | T44: =$R$37+S44 -> 0.0596
D45: 0.3 | E45: =H16 -> 0.12310784 | F45: =M30 -> 0.03403075 | G45: =((E45*(100%-D45))+(F45*D45)) -> 0.096384713 | Q45: 2.25 –2.5 | R45: Ba1/BB+ | S45: 0.03 | T45: =$R$37+S45 -> 0.0696
D46: 0.4 | E46: =H17 -> 0.13390199 | F46: =M31 -> 0.035092 | G46: =((E46*(100%-D46))+(F46*D46)) -> 0.094377996 | Q46: 2 –2.25 | R46: Ba2/BB | S46: 0.04 | T46: =$R$37+S46 -> 0.0796
D47: 0.5 | E47: =H18 -> 0.14901381 | F47: =M32 -> 0.0372145 | G47: =((E47*(100%-D47))+(F47*D47)) -> 0.093114154 | Q47: 1.75 -2 | R47: B1/B+ | S47: 0.055 | T47: =$R$37+S47 -> 0.0946
D48: 0.6 | E48: =H19 -> 0.17168153 | F48: =M33 -> 0.0372145 | G48: =((E48*(100%-D48))+(F48*D48)) -> 0.091001312 | Q48: 1.5 –1.75 | R48: B2/B | S48: 0.065 | T48: =$R$37+S48 -> 0.1046
D49: 0.7 | E49: =H20 -> 0.20946106 | F49: =M34 -> 0.042167 | G49: =((E49*(100%-D49))+(F49*D49)) -> 0.092355219 | Q49: 1.25 -1.5 | R49: B3/B- | S49: 0.0725 | T49: =$R$37+S49 -> 0.1121
D50: 0.8 | E50: =H21 -> 0.28502014 | F50: =M35 -> 0.049242 | G50: =((E50*(100%-D50))+(F50*D50)) -> 0.096397627 | Q50: 0.8 -1.25 | R50: Caa/CCC | S50: 0.0875 | T50: =$R$37+S50 -> 0.1271
D51: 0.9 | E51: =H22 -> 0.51169735 | F51: =M36 -> 0.056317 | G51: =((E51*(100%-D51))+(F51*D51)) -> 0.10185504 | Q51: 0.65 –0.8 | R51: Ca2/CC | S51: 0.095 | T51: =$R$37+S51 -> 0.1346
Q52: 0.2 –0.65 | R52: C2/C | S52: 0.105 | T52: =$R$37+S52 -> 0.1446
Q53: <0.2 | R53: D2/D | S53: 0.12 | T53: =$R$37+S53 -> 0.1596

Sheet ⛔️WACC Approach Puma
A1: Risk-Free Rate (Rf) | B1: ='Credit Rating'!C43 -> 0.0248 | C1: T Bond Rate
A2: Market Risk Premium (Rm - Rf) | B2: 0.057 | C2: https://www.statista.com/statistics/664825/average-market-risk-premium-germany-europe/
A3: Marginal Tax Rate | B3: 0.3 | C3: spglobal
A4: Levered Beta (βL) | B4: 1.08 | C4: https://finance.yahoo.com/quote/PBYI/
A5: Unlevered Beta (βU) | B5: =Q6 -> 0.76014188 | P5: Step-2
A6: Total Debt (D) | B6: =Competitors!AA207 -> 4058100000 | P6: Unlevered beta | Q6: =B4/(1+(1-B3)*(B6/B7)) -> 0.76014188
A7: Total Equity € | B7: =Dividend!O26*Competitors!AA64 -> 6.7508439e+09 | C7: As of Dec 2023
A8: EBIT | B8: =Competitors!AA73 -> 715800000
A10: Pre-Tax Cost of Debt | G10: Step-3
F11: Estimate Cost of Equity
E12: Debt to Capital Ratio | F12: D/E Ratio | G12: Levered Beta | H12: Cost of Equity
A13: =B6/(B6+B7) -> 0.37543908 | E13: 0 | F13: =E13/(1-E13) -> 0 | G13: =$Q$6*(1+(1-$B$3)*(F13)) -> 0.76014188 | H13: =$B$1+G13*$B$2 -> 0.068128087
E14: 0.1 | F14: =E14/(1-E14) -> 0.11111111 | G14: =$Q$6*(1+(1-$B$3)*(F14)) -> 0.81926403 | H14: =$B$1+G14*$B$2 -> 0.07149805
E15: 0.2 | F15: =E15/(1-E15) -> 0.25 | G15: =$Q$6*(1+(1-$B$3)*(F15)) -> 0.89316671 | H15: =$B$1+G15*$B$2 -> 0.075710502
E16: 0.3 | F16: =E16/(1-E16) -> 0.42857143 | G16: =$Q$6*(1+(1-$B$3)*(F16)) -> 0.98818444 | H16: =$B$1+G16*$B$2 -> 0.081126513
E17: 0.4 | F17: =E17/(1-E17) -> 0.66666667 | G17: =$Q$6*(1+(1-$B$3)*(F17)) -> 1.1148748 | H17: =$B$1+G17*$B$2 -> 0.088347861
E18: 0.5 | F18: =E18/(1-E18) -> 1 | G18: =$Q$6*(1+(1-$B$3)*(F18)) -> 1.2922412 | H18: =$B$1+G18*$B$2 -> 0.098457748
E19: 0.6 | F19: =E19/(1-E19) -> 1.5 | G19: =$Q$6*(1+(1-$B$3)*(F19)) -> 1.5582909 | H19: =$B$1+G19*$B$2 -> 0.11362258
E20: 0.7 | F20: =E20/(1-E20) -> 2.3333333 | G20: =$Q$6*(1+(1-$B$3)*(F20)) -> 2.001707 | H20: =$B$1+G20*$B$2 -> 0.1388973
E21: 0.8 | F21: =E21/(1-E21) -> 4 | G21: =$Q$6*(1+(1-$B$3)*(F21)) -> 2.8885391 | H21: =$B$1+G21*$B$2 -> 0.18944673
E22: 0.9 | F22: =E22/(1-E22) -> 9 | G22: =$Q$6*(1+(1-$B$3)*(F22)) -> 5.5490357 | H22: =$B$1+G22*$B$2 -> 0.34109504
E24: Pre-Tax Cost of Debt | F24: =B1 -> 0.0248
E25: Estimate Cost of Debts
D26: Debt to Capital Ratio | E26: D/E Ratio | F26: Debt | G26: EBIT | H26: Interest | I26: Pre-Tax Int. Cov | J26: Likely Rating | K26: Pre-Tax cost of debt | L26: Tax Rate | M26: After Tax Cost of Debt
D27: 0 | E27: =D27/(1-D27) -> 0 | F27: =$B$7*D27 -> 0 | G27: =$B$8 -> 715800000 | H27: =F27*$F$24 -> 0 | I27: =G27/H27 -> #DIV/0! | J27: =S41 -> Aaa/AAA | K27: =U41 -> 0.0288 | L27: =$B$3 -> 0.3 | M27: =K27*(1-L27) -> 0.02016
D28: 0.1 | E28: =D28/(1-D28) -> 0.11111111 | F28: =$B$7*D28 -> 6.7508439e+08 | G28: =$B$8 -> 715800000 | H28: =F28*$F$24 -> 16742093 | I28: =G28/H28 -> 42.754511 | J28: =S41 -> Aaa/AAA | K28: =U41 -> 0.0288 | L28: =$B$3 -> 0.3 | M28: =K28*(1-L28) -> 0.02016
D29: 0.2 | E29: =D29/(1-D29) -> 0.25 | F29: =$B$7*D29 -> 1.3501688e+09 | G29: =$B$8 -> 715800000 | H29: =F29*$F$24 -> 33484186 | I29: =G29/H29 -> 21.377256 | J29: =S41 -> Aaa/AAA | K29: =U41 -> 0.0288 | L29: =$B$3 -> 0.3 | M29: =K29*(1-L29) -> 0.02016
D30: 0.3 | E30: =D30/(1-D30) -> 0.42857143 | F30: =$B$7*D30 -> 2.0252532e+09 | G30: =$B$8 -> 715800000 | H30: =F30*$F$24 -> 50226279 | I30: =G30/H30 -> 14.251504 | J30: =S41 -> Aaa/AAA | K30: =U41 -> 0.0288 | L30: =$B$3 -> 0.3 | M30: =K30*(1-L30) -> 0.02016
D31: 0.4 | E31: =D31/(1-D31) -> 0.66666667 | F31: =$B$7*D31 -> 2.7003376e+09 | G31: =$B$8 -> 715800000 | H31: =F31*$F$24 -> 66968372 | I31: =G31/H31 -> 10.688628 | J31: =S41 -> Aaa/AAA | K31: =U41 -> 0.0288 | L31: =$B$3 -> 0.3 | M31: =K31*(1-L31) -> 0.02016
D32: 0.5 | E32: =D32/(1-D32) -> 1 | F32: =$B$7*D32 -> 3.375422e+09 | G32: =$B$8 -> 715800000 | H32: =F32*$F$24 -> 83710464 | I32: =G32/H32 -> 8.5509023 | J32: =S41 -> Aaa/AAA | K32: =U41 -> 0.0288 | L32: =$B$3 -> 0.3 | M32: =K32*(1-L32) -> 0.02016
D33: 0.6 | E33: =D33/(1-D33) -> 1.5 | F33: =$B$7*D33 -> 4.0505063e+09 | G33: =$B$8 -> 715800000 | H33: =F33*$F$24 -> 1.0045256e+08 | I33: =G33/H33 -> 7.1257519 | J33: =S42 -> Aa2/AA | K33: =U42 -> 0.0318 | L33: =$B$3 -> 0.3 | M33: =K33*(1-L33) -> 0.02226
D34: 0.7 | E34: =D34/(1-D34) -> 2.3333333 | F34: =$B$7*D34 -> 4.7255907e+09 | G34: =$B$8 -> 715800000 | H34: =F34*$F$24 -> 1.1719465e+08 | I34: =G34/H34 -> 6.1077873 | J34: =S43 -> A1/A+ | K34: =U43 -> 0.0333 | L34: =$B$3 -> 0.3 | M34: =K34*(1-L34) -> 0.02331
D35: 0.8 | E35: =D35/(1-D35) -> 4 | F35: =$B$7*D35 -> 5.4006751e+09 | G35: =$B$8 -> 715800000 | H35: =F35*$F$24 -> 1.3393674e+08 | I35: =G35/H35 -> 5.3443139 | J35: =S44 -> A2/A | K35: =U44 -> 0.0348 | L35: =$B$3 -> 0.3 | M35: =K35*(1-L35) -> 0.02436
D36: 0.9 | E36: =D36/(1-D36) -> 9 | F36: =$B$7*D36 -> 6.0757595e+09 | G36: =$B$8 -> 715800000 | H36: =F36*$F$24 -> 1.5067884e+08 | I36: =G36/H36 -> 4.7505013 | J36: =S44 -> A2/A | K36: =U44 -> 0.0348 | L36: =$B$3 -> 0.3 | M36: =K36*(1-L36) -> 0.02436
R39: T Bond Rate | S39: =B1 -> 0.0248 | T39: German Rates & Bonds - Bloomberg
E40: Puma´s Cost of Capital Schedule | R40: Interest Coverage Ratio | S40: Rating | T40: Spread (%) | U40: Interest Rate (%)
D41: Debt to Capital Ratio | E41: Cost of Equity | F41: After-tax Cost of Debt | G41: Cost of Capital | R41: > 8.50 | S41: Aaa/AAA | T41: 0.004 | U41: =$S$39+T41 -> 0.0288
D42: 0 | E42: =H13 -> 0.068128087 | F42: =M27 -> 0.02016 | G42: =((E42*(100%-D42))+(F42*D42)) -> 0.068128087 | R42: 6.5 –8.5 | S42: Aa2/AA | T42: 0.007 | U42: =$S$39+T42 -> 0.0318
D43: 0.1 | E43: =H14 -> 0.07149805 | F43: =M28 -> 0.02016 | G43: =((E43*(100%-D43))+(F43*D43)) -> 0.066364245 | R43: 5.5 –6.5 | S43: A1/A+ | T43: 0.0085 | U43: =$S$39+T43 -> 0.0333
D44: 0.2 | E44: =H15 -> 0.075710502 | F44: =M29 -> 0.02016 | G44: =((E44*(100%-D44))+(F44*D44)) -> 0.064600402 | R44: 4.25 –5.5 | S44: A2/A | T44: 0.01 | U44: =$S$39+T44 -> 0.0348
D45: 0.3 | E45: =H16 -> 0.081126513 | F45: =M30 -> 0.02016 | G45: =((E45*(100%-D45))+(F45*D45)) -> 0.062836559 | R45: 3 –4.25 | S45: A3/A- | T45: 0.013 | U45: =$S$39+T45 -> 0.0378
D46: 0.4 | E46: =H17 -> 0.088347861 | F46: =M31 -> 0.02016 | G46: =((E46*(100%-D46))+(F46*D46)) -> 0.061072717 | R46: 2.5 -3 | S46: Baa2/BBB | T46: 0.02 | U46: =$S$39+T46 -> 0.0448
D47: 0.5 | E47: =H18 -> 0.098457748 | F47: =M32 -> 0.02016 | G47: =((E47*(100%-D47))+(F47*D47)) -> 0.059308874 | R47: 2.25 –2.5 | S47: Ba1/BB+ | T47: 0.03 | U47: =$S$39+T47 -> 0.0548
D48: 0.6 | E48: =H19 -> 0.11362258 | F48: =M33 -> 0.02226 | G48: =((E48*(100%-D48))+(F48*D48)) -> 0.058805032 | R48: 2 –2.25 | S48: Ba2/BB | T48: 0.04 | U48: =$S$39+T48 -> 0.0648
D49: 0.7 | E49: =H20 -> 0.1388973 | F49: =M34 -> 0.02331 | G49: =((E49*(100%-D49))+(F49*D49)) -> 0.057986189 | R49: 1.75 -2 | S49: B1/B+ | T49: 0.055 | U49: =$S$39+T49 -> 0.0798
D50: 0.8 | E50: =H21 -> 0.18944673 | F50: =M35 -> 0.02436 | G50: =((E50*(100%-D50))+(F50*D50)) -> 0.057377346 | R50: 1.5 –1.75 | S50: B2/B | T50: 0.065 | U50: =$S$39+T50 -> 0.0898
D51: 0.9 | E51: =H22 -> 0.34109504 | F51: =M36 -> 0.02436 | G51: =((E51*(100%-D51))+(F51*D51)) -> 0.056033504 | R51: 1.25 -1.5 | S51: B3/B- | T51: 0.0725 | U51: =$S$39+T51 -> 0.0973
R52: 0.8 -1.25 | S52: Caa/CCC | T52: 0.0875 | U52: =$S$39+T52 -> 0.1123
R53: 0.65 –0.8 | S53: Ca2/CC | T53: 0.095 | U53: =$S$39+T53 -> 0.1198
R54: 0.2 –0.65 | S54: C2/C | T54: 0.105 | U54: =$S$39+T54 -> 0.1298
R55: <0.2 | S55: D2/D | T55: 0.12 | U55: =$S$39+T55 -> 0.1448

Sheet WACC Approach Adidas
A1: Risk-Free Rate (Rf) | B1: ='Credit Rating'!C43 -> 0.0248 | C1: T Bond Rate
A2: Market Risk Premium (Rm - Rf) | B2: 0.057 | C2: https://www.statista.com/statistics/664825/average-market-risk-premium-germany-europe/
A3: Marginal Tax Rate | B3: 0.3 | C3: spglobal
A4: Levered Beta (βL) | B4: 1.16 | I4: adidas AG (ADS.DE) Stock Price, News, Quote & History - Yahoo Finance
A5: Unlevered Beta (βU) | B5: =Q6 -> 0.82691984 | P5: Step-2
A6: Total Debt (D) | B6: =ADDDF!F73 -> 13095000000 | P6: Unlevered beta | Q6: =B4/(1+(1-B3)*(B6/B7)) -> 0.82691984
A7: Value of equity based on market | B7: =Dividend!N23*'Income Statement'!F69 -> 2.2757167e+10 | C7: As of Dec 2023 | D7: adidas AG (ADS.DE) Stock Historical Prices & Data - Yahoo Finance
A8: EBIT | B8: ='Income Statement'!F85 -> 442000000
A9: EBIT Interest Coverage Ratio | B9: =Ratios!G11 -> 2.7116564
A10: Pre-Tax Cost of Debt | G10: Step-3
C11: =B7/Dividend!O23 -> 1.235728e+08 | F11: Estimate Cost of Equity
E12: Debt to Capital Ratio | F12: D/E Ratio | G12: Levered Beta | H12: Cost of Equity
A13: =B6/(B6+B7) -> 0.36524989 | E13: 0 | F13: =E13/(1-E13) -> 0 | G13: =$Q$6*(1+(1-$B$3)*(F13)) -> 0.82691984 | H13: =$B$1+G13*$B$2 -> 0.071934431
E14: 0.1 | F14: =E14/(1-E14) -> 0.11111111 | G14: =$Q$6*(1+(1-$B$3)*(F14)) -> 0.89123583 | H14: =$B$1+G14*$B$2 -> 0.075600442
E15: 0.2 | F15: =E15/(1-E15) -> 0.25 | G15: =$Q$6*(1+(1-$B$3)*(F15)) -> 0.97163081 | H15: =$B$1+G15*$B$2 -> 0.080182956
A16: Free Cash flow to firm | B16: =B8*(1-B3)+'Cash Flow Statement'!F7-(-'Cash Flow Statement'!F31-'Cash Flow Statement'!F34-'Cash Flow Statement'!F37-'Cash Flow Statement'!F40)-0 -> 964400000 | E16: 0.3 | F16: =E16/(1-E16) -> 0.42857143 | G16: =$Q$6*(1+(1-$B$3)*(F16)) -> 1.0749958 | H16: =$B$1+G16*$B$2 -> 0.08607476
A17: Wacc | B17: =(B19*((Dividend!O23*'Income Statement'!F69)/(B6+(Dividend!O23*'Income Statement'!F69))))+B20*(B6/(B6+(Dividend!O23*'Income Statement'!F69))) -> 0.072560176 | E17: 0.4 | F17: =E17/(1-E17) -> 0.66666667 | G17: =$Q$6*(1+(1-$B$3)*(F17)) -> 1.2128158 | H17: =$B$1+G17*$B$2 -> 0.093930499
A18: Current enterprize value | B18: =B7+B6-B16 -> 3.4887767e+10 | E18: 0.5 | F18: =E18/(1-E18) -> 1 | G18: =$Q$6*(1+(1-$B$3)*(F18)) -> 1.4057637 | H18: =$B$1+G18*$B$2 -> 0.10492853
A19: Cost of Equity | B19: =B1+B4*B2 -> 0.09092 | E19: 0.6 | F19: =E19/(1-E19) -> 1.5 | G19: =$Q$6*(1+(1-$B$3)*(F19)) -> 1.6951857 | H19: =$B$1+G19*$B$2 -> 0.12142558
A20: After tax cost of debt | B20: ='Credit Rating'!E49* (1-'WACC Approach Adidas'!B3) -> 0.02646 | E20: 0.7 | F20: =E20/(1-E20) -> 2.3333333 | G20: =$Q$6*(1+(1-$B$3)*(F20)) -> 2.1775556 | H20: =$B$1+G20*$B$2 -> 0.14892067
A21: Growth Rate | B21: =(B18*B17-B16)/(B18+B16) -> 0.043709004 | E21: 0.8 | F21: =E21/(1-E21) -> 4 | G21: =$Q$6*(1+(1-$B$3)*(F21)) -> 3.1422954 | H21: =$B$1+G21*$B$2 -> 0.20391084
E22: 0.9 | F22: =E22/(1-E22) -> 9 | G22: =$Q$6*(1+(1-$B$3)*(F22)) -> 6.0365148 | H22: =$B$1+G22*$B$2 -> 0.36888135
E24: Risk Free Rate | F24: 0.0248
A25: Firm Value with optimal wacc | B25: =(B16*(1+B21))/(G44-B21) -> 3.7685401e+10 | E25: Estimate Cost of Debts
D26: Debt to Capital Ratio | E26: D/E Ratio | F26: Debt | G26: EBIT | H26: Interest | I26: Pre-Tax Int. Cov | J26: Likely Rating | K26: Pre-Tax cost of debt | L26: Tax Rate | M26: After Tax Cost of Debt
D27: 0 | E27: =D27/(1-D27) -> 0 | F27: =$B$7*D27 -> 0 | G27: =$B$8 -> 442000000 | H27: =F27*$F$24 -> 0 | I27: =G27/H27 -> #DIV/0! | J27: ='Credit Rating'!C45 -> Aaa/AAA | K27: =B1+'Credit Rating'!D45 -> 0.0288 | L27: =$B$3 -> 0.3 | M27: =K27*(1-L27) -> 0.02016
A28: Increase in firm value | B28: =B25-B7 -> 1.4928234e+10 | C28: ?????? | D28: 0.1 | E28: =D28/(1-D28) -> 0.11111111 | F28: =$B$7*D28 -> 2.2757167e+09 | G28: =$B$8 -> 442000000 | H28: =F28*$F$24 -> 56437774 | I28: =G28/H28 -> 7.8316342 | J28: ='Credit Rating'!C48 -> A2/A | K28: ='WACC Approach Adidas'!B1+'Credit Rating'!D48 -> 0.0348 | L28: =$B$3 -> 0.3 | M28: =K28*(1-L28) -> 0.02436
D29: 0.2 | E29: =D29/(1-D29) -> 0.25 | F29: =$B$7*D29 -> 4.5514333e+09 | G29: =$B$8 -> 442000000 | H29: =F29*$F$24 -> 1.1287555e+08 | I29: =G29/H29 -> 3.9158171 | J29: ='Credit Rating'!C50 -> Baa2/BBB | K29: =B1+'Credit Rating'!D50 -> 0.0448 | L29: =$B$3 -> 0.3 | M29: =K29*(1-L29) -> 0.03136
D30: 0.3 | E30: =D30/(1-D30) -> 0.42857143 | F30: =$B$7*D30 -> 6.82715e+09 | G30: =$B$8 -> 442000000 | H30: =F30*$F$24 -> 1.6931332e+08 | I30: =G30/H30 -> 2.6105447 | J30: ='Credit Rating'!C53 -> B1/B+ | K30: =B1+'Credit Rating'!D53 -> 0.0798 | L30: =$B$3 -> 0.3 | M30: =K30*(1-L30) -> 0.05586
D31: 0.4 | E31: =D31/(1-D31) -> 0.66666667 | F31: =$B$7*D31 -> 9.1028667e+09 | G31: =$B$8 -> 442000000 | H31: =F31*$F$24 -> 2.2575109e+08 | I31: =G31/H31 -> 1.9579086 | J31: ='Credit Rating'!C55 -> B3/B- | K31: =B1+'Credit Rating'!D55 -> 0.0973 | L31: =$B$3 -> 0.3 | M31: =K31*(1-L31) -> 0.06811
D32: 0.5 | E32: =D32/(1-D32) -> 1 | F32: =$B$7*D32 -> 1.1378583e+10 | G32: =$B$8 -> 442000000 | H32: =F32*$F$24 -> 2.8218887e+08 | I32: =G32/H32 -> 1.5663268 | J32: ='Credit Rating'!C56 -> Caa/CCC | K32: =B1+'Credit Rating'!D56 -> 0.1123 | L32: =30% -> 0.3 | M32: =K32*(1-L32) -> 0.07861
D33: 0.6 | E33: =D33/(1-D33) -> 1.5 | F33: =$B$7*D33 -> 1.36543e+10 | G33: =$B$8 -> 442000000 | H33: =F33*$F$24 -> 3.3862664e+08 | I33: =G33/H33 -> 1.3052724 | J33: ='Credit Rating'!C56 -> Caa/CCC | K33: =B1+'Credit Rating'!D56 -> 0.1123 | L33: =30% -> 0.3 | M33: =K33*(1-L33) -> 0.07861
D34: 0.7 | E34: =D34/(1-D34) -> 2.3333333 | F34: =$B$7*D34 -> 1.5930017e+10 | G34: =$B$8 -> 442000000 | H34: =F34*$F$24 -> 3.9506441e+08 | I34: =G34/H34 -> 1.1188049 | J34: ='Credit Rating'!C57 -> Ca2/CC | K34: =B1+'Credit Rating'!D57 -> 0.1198 | L34: =30% -> 0.3 | M34: =K34*(1-L34) -> 0.08386
D35: 0.8 | E35: =D35/(1-D35) -> 4 | F35: =$B$7*D35 -> 1.8205733e+10 | G35: =$B$8 -> 442000000 | H35: =F35*$F$24 -> 4.5150219e+08 | I35: =G35/H35 -> 0.97895428 | J35: ='Credit Rating'!C57 -> Ca2/CC | K35: =B1+'Credit Rating'!D58 -> 0.1298 | L35: =(G35*$B$3)/H35 -> 0.29368628 | M35: =K35*(1-L35) -> 0.09167952
D36: 0.9 | E36: =D36/(1-D36) -> 9 | F36: =$B$7*D36 -> 2.048145e+10 | G36: =$B$8 -> 442000000 | H36: =F36*$F$24 -> 5.0793996e+08 | I36: =G36/H36 -> 0.87018158 | J36: ='Credit Rating'!C58 -> C2/C | K36: =B1+'Credit Rating'!D58 -> 0.1298 | L36: =(G36*$B$3)/H36 -> 0.26105447 | M36: =K36*(1-L36) -> 0.095915129
E40: Adidas´s Cost of Capital Schedule
D41: Debt to Capital Ratio | E41: Cost of Equity | F41: After-tax Cost of Debt | G41: Cost of Capital
D42: 0 | E42: =H13 -> 0.071934431 | F42: =M27 -> 0.02016 | G42: =((E42*(1-D42))+(F42*D42)) -> 0.071934431
D43: 0.1 | E43: =H14 -> 0.075600442 | F43: =M28 -> 0.02436 | G43: =((E43*(100%-D43))+(F43*D43)) -> 0.070476398
D44: 0.2 | E44: =H15 -> 0.080182956 | F44: =M29 -> 0.03136 | G44: =((E44*(100%-D44))+(F44*D44)) -> 0.070418365
D45: 0.3 | E45: =H16 -> 0.08607476 | F45: =M30 -> 0.05586 | G45: =((E45*(100%-D45))+(F45*D45)) -> 0.077010332
D46: 0.4 | E46: =H17 -> 0.093930499 | F46: =M31 -> 0.06811 | G46: =((E46*(100%-D46))+(F46*D46)) -> 0.083602299
D47: 0.5 | E47: =H18 -> 0.10492853 | F47: =M32 -> 0.07861 | G47: =((E47*(100%-D47))+(F47*D47)) -> 0.091769266
D48: 0.6 | E48: =H19 -> 0.12142558 | F48: =M33 -> 0.07861 | G48: =((E48*(100%-D48))+(F48*D48)) -> 0.095736233
D49: 0.7 | E49: =H20 -> 0.14892067 | F49: =M34 -> 0.08386 | G49: =((E49*(100%-D49))+(F49*D49)) -> 0.1033782
D50: 0.8 | E50: =H21 -> 0.20391084 | F50: =M35 -> 0.09167952 | G50: =((E50*(100%-D50))+(F50*D50)) -> 0.11412578
D51: 0.9 | E51: =H22 -> 0.36888135 | F51: =M36 -> 0.095915129 | G51: =((E51*(100%-D51))+(F51*D51)) -> 0.12321175
D79: WACC Statistics For the Industry
F185: ='Dividend'!O23*

Sheet Written part
A1: We wrote the content based on our own ideas and used AI to enhance the quality of the language and refine the English.

Sheet Dividend
B1: Dividend per share
B3: Comapany Name | C3: 2019 | D3: 2020 | E3: 2021 | F3: 2022 | G3: 2023
B4: Adidas | C4: ='Income Statement'!B71 -> 3.35 | D4: ='Income Statement'!C71 -> 0 | E4: ='Income Statement'!D71 -> 3 | F4: ='Income Statement'!E71 -> 3.3 | G4: ='Income Statement'!F71 -> 0.7
B5: Nike | C5: =Competitors!B40 -> 0.86 | D5: =Competitors!C40 -> 0.95 | E5: =Competitors!D40 -> 1.07 | F5: =Competitors!E40 -> 1.19 | G5: =Competitors!F40 -> 1.32
B6: Under Armour | C6: 0 | D6: 0 | E6: 0 | F6: 0 | G6: 0
B7: Puma | C7: =Competitors!W66 -> 0.35 | D7: =Competitors!X66 -> 0 | E7: =Competitors!Y66 -> 0.16 | F7: =Competitors!Z66 -> 0.72 | G7: =Competitors!AA66 -> 0.82
B11: Dividend payout ratio
B13: Comapany Name | C13: 2019 | D13: 2020 | E13: 2021 | F13: 2022 | G13: 2023
B14: Adidas | C14: =C4/'Income Statement'!B75 -> 0.335 | D14: =D4/'Income Statement'!C75 -> 0 | E14: =E4/'Income Statement'!D75 -> 0.27522936 | F14: =F4/'Income Statement'!E75 -> 0.98802395 | G14: =G4/'Income Statement'!F75 -> -1.6666667
B15: Nike | C15: =C5/Competitors!B42 -> 0.3372549 | D15: =D5/Competitors!C42 -> 0.58282209 | E15: =E5/Competitors!D42 -> 0.29395604 | F15: =F5/Competitors!E42 -> 0.31070496 | G15: =G5/Competitors!F42 -> 0.40366972
B16: Under Armour | C16: =C6/Competitors!L47 -> 0 | D16: =D6/Competitors!M47 -> 0 | E16: =E6/Competitors!N47 -> 0 | F16: =F6/Competitors!O47 -> 0 | G16: =G6/Competitors!P47 -> 0
B17: Puma | C17: =C7/Competitors!W69 -> 0.19886364 | D17: =D7/Competitors!X69 -> 0 | E17: =E7/Competitors!Y69 -> 0.077294686 | F17: =F7/Competitors!Z69 -> 0.30508475 | G17: =G7/Competitors!AA69 -> 0.40394089
B20: Dividend yield | J20: Share Price (End of year) - Close price
B21: Dividends per share/Share Price
B22: Comapany Name | C22: 2019 | D22: 2020 | E22: 2021 | F22: 2022 | G22: 2023 | J22: Comapany Name | K22: 2019 | L22: 2020 | M22: 2021 | N22: 2022 | O22: 2023
B23: Adidas | C23: =C4/K23 -> 0.011559696 | D23: =D4/L23 -> 0 | E23: =E4/M23 -> 0.011848341 | F23: =F4/N23 -> 0.025890475 | G23: =G4/O23 -> 0.0038010426 | J23: Adidas | K23: 289.8 | L23: 297.9 | M23: 253.2 | N23: 127.46 | O23: 184.16 | P23: Yahoo finance
B24: Nike | C24: =C5/K24 -> 0.0084887968 | D24: =D5/L24 -> 0.0067152046 | E24: =E5/M24 -> 0.0064198716 | F24: =F5/N24 -> 0.010960671 | G24: =G5/O24 -> 0.017444165 | J24: Nike | K24: 101.31 | L24: 141.47 | M24: 166.67 | N24: 108.57 | O24: 75.67 | P24: Yahoo finance
B25: Under Armour | C25: =C6/K25 -> 0 | D25: =D6/L25 -> 0 | E25: =E6/M25 -> 0 | F25: =F6/N25 -> 0 | G25: =G6/O25 -> 0 | J25: Under Armour | K25: 17.17 | L25: 21.19 | M25: 21.19 | N25: 9.96 | O25: 8.79 | P25: Yahoo finance
B26: Puma | C26: =C7/K26 -> 0.0051207023 | D26: =D7/L26 -> 0 | E26: =E7/M26 -> 0.0014883721 | F26: =F7/N26 -> 0.012698413 | G26: =G7/O26 -> 0.018201998 | J26: Puma | K26: 68.35 | L26: 92.28 | M26: 107.5 | N26: 56.7 | O26: 45.05 | P26: Yahoo finance
B32: Share buybacks
B34: Comapany Name | C34: 2019 | D34: 2020 | E34: 2021 | F34: 2022 | G34: 2023 | H34: Total
B35: Adidas | C35: =-'Cash Flow Statement'!B50 -> 837000000 | D35: =-'Cash Flow Statement'!C50 -> 286000000 | E35: =-'Cash Flow Statement'!D50 -> 1032000000 | F35: =-'Cash Flow Statement'!E50 -> 2530000000 | G35: =-'Cash Flow Statement'!F50 -> 29000000 | H35: =SUM(Table5[[#This Row],[2019]:[2023]]) -> 4714000000
B36: Nike | C36: =-Competitors!B89 -> 4286000000 | D36: =-Competitors!C89 -> 3067000000 | E36: =-Competitors!D89 -> 608000000 | F36: =-Competitors!E89 -> 4014000000 | G36: =-Competitors!F89 -> 5480000000 | H36: =SUM(Table5[[#This Row],[2019]:[2023]]) -> 17455000000
B37: Under Armour | C37: 0 | D37: 0 | E37: 0 | F37: 0 | G37: 0 | H37: =SUM(Table5[[#This Row],[2019]:[2023]]) -> 0
B38: Puma | C38: 0 | D38: 0 | E38: 0 | F38: 0 | G38: 0 | H38: =SUM(Table5[[#This Row],[2019]:[2023]]) -> 0
B41: Adidas Dividend Yield | C41: =C23 -> 0.011559696 | D41: =D23 -> 0 | E41: =E23 -> 0.011848341 | F41: =F23 -> 0.025890475 | G41: =G23 -> 0.0038010426
B42: Adidas Dividend Payout ratio | C42: =C14 -> 0.335 | D42: =D14 -> 0 | E42: =E14 -> 0.27522936 | F42: =F14 -> 0.98802395 | G42: =G14 -> -1.6666667
N62: =O23*'Income Statement'!F69 -> 3.2880589e+10
J90: =C4/ADDDF!J95 -> #DIV/0!
